{
"meta":{"test_sets":[],"test_metrics":[],"learn_metrics":[{"best_value":"Min","name":"RMSE"}],"launch_mode":"Train","parameters":"","iteration_count":1000,"learn_sets":["learn"],"name":"experiment"},
"iterations":[
{"learn":[1865.007966],"iteration":0,"passed_time":0.1831107345,"remaining_time":182.9276238},
{"learn":[1811.6906],"iteration":1,"passed_time":0.1877806398,"remaining_time":93.70253926},
{"learn":[1761.297096],"iteration":2,"passed_time":0.1921037396,"remaining_time":63.84247612},
{"learn":[1713.324107],"iteration":3,"passed_time":0.197102702,"remaining_time":49.07857281},
{"learn":[1673.925419],"iteration":4,"passed_time":0.2015123401,"remaining_time":40.10095567},
{"learn":[1624.975621],"iteration":5,"passed_time":0.2045239778,"remaining_time":33.88280565},
{"learn":[1578.061975],"iteration":6,"passed_time":0.2074342848,"remaining_time":29.42603498},
{"learn":[1536.06952],"iteration":7,"passed_time":0.2101620071,"remaining_time":26.06008888},
{"learn":[1493.025071],"iteration":8,"passed_time":0.2126643378,"remaining_time":23.41670653},
{"learn":[1456.328308],"iteration":9,"passed_time":0.2146809397,"remaining_time":21.25341303},
{"learn":[1417.842677],"iteration":10,"passed_time":0.2166423204,"remaining_time":19.47811408},
{"learn":[1387.016913],"iteration":11,"passed_time":0.2184568959,"remaining_time":17.98628443},
{"learn":[1352.585296],"iteration":12,"passed_time":0.220107285,"remaining_time":16.71122233},
{"learn":[1314.590323],"iteration":13,"passed_time":0.2216772827,"remaining_time":15.61241434},
{"learn":[1277.890892],"iteration":14,"passed_time":0.2235007662,"remaining_time":14.67655031},
{"learn":[1243.717336],"iteration":15,"passed_time":0.225202643,"remaining_time":13.84996255},
{"learn":[1210.473035],"iteration":16,"passed_time":0.2266422354,"remaining_time":13.10525397},
{"learn":[1179.262266],"iteration":17,"passed_time":0.2280896491,"remaining_time":12.44355753},
{"learn":[1151.261467],"iteration":18,"passed_time":0.2294484119,"remaining_time":11.84678379},
{"learn":[1121.356349],"iteration":19,"passed_time":0.2308338363,"remaining_time":11.31085798},
{"learn":[1093.168319],"iteration":20,"passed_time":0.2323167491,"remaining_time":10.83038559},
{"learn":[1066.006198],"iteration":21,"passed_time":0.2336724805,"remaining_time":10.38780391},
{"learn":[1040.668909],"iteration":22,"passed_time":0.2350683351,"remaining_time":9.985294062},
{"learn":[1016.605606],"iteration":23,"passed_time":0.2363039944,"remaining_time":9.609695772},
{"learn":[990.3225727],"iteration":24,"passed_time":0.2380519103,"remaining_time":9.2840245},
{"learn":[970.4734674],"iteration":25,"passed_time":0.2392514137,"remaining_time":8.962726038},
{"learn":[946.1669805],"iteration":26,"passed_time":0.2403033232,"remaining_time":8.659819759},
{"learn":[921.0833663],"iteration":27,"passed_time":0.2413832795,"remaining_time":8.37944813},
{"learn":[896.4767031],"iteration":28,"passed_time":0.242620657,"remaining_time":8.123608896},
{"learn":[877.0112879],"iteration":29,"passed_time":0.2437871086,"remaining_time":7.882449844},
{"learn":[856.448103],"iteration":30,"passed_time":0.2448716922,"remaining_time":7.654215154},
{"learn":[834.7460416],"iteration":31,"passed_time":0.2458836166,"remaining_time":7.437979401},
{"learn":[814.6303824],"iteration":32,"passed_time":0.2470224896,"remaining_time":7.238507498},
{"learn":[793.9718759],"iteration":33,"passed_time":0.2481774856,"remaining_time":7.051160325},
{"learn":[774.2553918],"iteration":34,"passed_time":0.2492582228,"remaining_time":6.872405285},
{"learn":[753.1915516],"iteration":35,"passed_time":0.2503911479,"remaining_time":6.704918515},
{"learn":[737.5721202],"iteration":36,"passed_time":0.2514710374,"remaining_time":6.545043487},
{"learn":[717.9360918],"iteration":37,"passed_time":0.2527140485,"remaining_time":6.397655649},
{"learn":[703.3120527],"iteration":38,"passed_time":0.2537556904,"remaining_time":6.252800473},
{"learn":[689.2550568],"iteration":39,"passed_time":0.2548572755,"remaining_time":6.116574613},
{"learn":[673.597262],"iteration":40,"passed_time":0.2559780513,"remaining_time":5.987389053},
{"learn":[657.1230026],"iteration":41,"passed_time":0.2575527026,"remaining_time":5.874654503},
{"learn":[639.0829395],"iteration":42,"passed_time":0.2594638009,"remaining_time":5.774578081},
{"learn":[622.2910797],"iteration":43,"passed_time":0.2610805084,"remaining_time":5.672567411},
{"learn":[606.4565683],"iteration":44,"passed_time":0.2622517133,"remaining_time":5.565564138},
{"learn":[594.1264145],"iteration":45,"passed_time":0.2630537562,"remaining_time":5.455506161},
{"learn":[582.8791907],"iteration":46,"passed_time":0.2641192398,"remaining_time":5.355439053},
{"learn":[570.0614543],"iteration":47,"passed_time":0.2651277467,"remaining_time":5.258366976},
{"learn":[555.6658219],"iteration":48,"passed_time":0.266140018,"remaining_time":5.16528892},
{"learn":[544.6483944],"iteration":49,"passed_time":0.267610979,"remaining_time":5.084608602},
{"learn":[531.8678352],"iteration":50,"passed_time":0.269121033,"remaining_time":5.007761966},
{"learn":[518.4194315],"iteration":51,"passed_time":0.2701907996,"remaining_time":4.925786115},
{"learn":[505.5725742],"iteration":52,"passed_time":0.2714724228,"remaining_time":4.850648761},
{"learn":[494.0022821],"iteration":53,"passed_time":0.2729432429,"remaining_time":4.781561255},
{"learn":[482.836822],"iteration":54,"passed_time":0.2741048602,"remaining_time":4.709619871},
{"learn":[474.4066191],"iteration":55,"passed_time":0.2752820455,"remaining_time":4.640468767},
{"learn":[464.4077087],"iteration":56,"passed_time":0.2764815465,"remaining_time":4.574071901},
{"learn":[454.451982],"iteration":57,"passed_time":0.2778236884,"remaining_time":4.512239905},
{"learn":[445.3968832],"iteration":58,"passed_time":0.2788741769,"remaining_time":4.447806788},
{"learn":[437.0012443],"iteration":59,"passed_time":0.2798541997,"remaining_time":4.384382462},
{"learn":[428.7854747],"iteration":60,"passed_time":0.280818775,"remaining_time":4.3227677},
{"learn":[420.1945924],"iteration":61,"passed_time":0.2821301695,"remaining_time":4.268356435},
{"learn":[412.5554163],"iteration":62,"passed_time":0.2837673384,"remaining_time":4.220476129},
{"learn":[404.441653],"iteration":63,"passed_time":0.2848800181,"remaining_time":4.166370264},
{"learn":[397.1735725],"iteration":64,"passed_time":0.2858951371,"remaining_time":4.112491588},
{"learn":[389.7709074],"iteration":65,"passed_time":0.2868537215,"remaining_time":4.059414787},
{"learn":[383.3674218],"iteration":66,"passed_time":0.2878897328,"remaining_time":4.008971951},
{"learn":[375.2284393],"iteration":67,"passed_time":0.288866635,"remaining_time":3.959172116},
{"learn":[367.9132455],"iteration":68,"passed_time":0.2898662883,"remaining_time":3.911094411},
{"learn":[360.8384878],"iteration":69,"passed_time":0.2908347363,"remaining_time":3.86394721},
{"learn":[353.1532759],"iteration":70,"passed_time":0.2918107496,"remaining_time":3.818199808},
{"learn":[345.3030497],"iteration":71,"passed_time":0.2927876994,"remaining_time":3.773708125},
{"learn":[340.2909293],"iteration":72,"passed_time":0.2937479483,"remaining_time":3.730196548},
{"learn":[333.6486926],"iteration":73,"passed_time":0.2947153705,"remaining_time":3.687924772},
{"learn":[327.5485041],"iteration":74,"passed_time":0.2956799508,"remaining_time":3.646719393},
{"learn":[322.0663879],"iteration":75,"passed_time":0.2966447679,"remaining_time":3.606575863},
{"learn":[316.8261727],"iteration":76,"passed_time":0.2979388811,"remaining_time":3.571397237},
{"learn":[311.7427525],"iteration":77,"passed_time":0.2990860829,"remaining_time":3.535350877},
{"learn":[306.1100603],"iteration":78,"passed_time":0.3001783615,"remaining_time":3.499547734},
{"learn":[301.4357602],"iteration":79,"passed_time":0.3012134926,"remaining_time":3.463955165},
{"learn":[295.3893719],"iteration":80,"passed_time":0.3025445234,"remaining_time":3.432573049},
{"learn":[290.0380867],"iteration":81,"passed_time":0.3036282756,"remaining_time":3.399155573},
{"learn":[286.0206493],"iteration":82,"passed_time":0.3046842776,"remaining_time":3.366210633},
{"learn":[281.1959057],"iteration":83,"passed_time":0.3057970668,"remaining_time":3.334644205},
{"learn":[277.1251758],"iteration":84,"passed_time":0.3070417554,"remaining_time":3.30521419},
{"learn":[272.4244622],"iteration":85,"passed_time":0.3089984786,"remaining_time":3.284007087},
{"learn":[268.0141856],"iteration":86,"passed_time":0.3101212416,"remaining_time":3.25449073},
{"learn":[263.2000249],"iteration":87,"passed_time":0.3121022085,"remaining_time":3.234513797},
{"learn":[259.6552876],"iteration":88,"passed_time":0.313450418,"remaining_time":3.208464391},
{"learn":[255.4778563],"iteration":89,"passed_time":0.3150070421,"remaining_time":3.185071203},
{"learn":[251.5868491],"iteration":90,"passed_time":0.3159998697,"remaining_time":3.156526171},
{"learn":[247.569386],"iteration":91,"passed_time":0.3169771005,"remaining_time":3.128426166},
{"learn":[243.7045716],"iteration":92,"passed_time":0.3179805072,"remaining_time":3.101164732},
{"learn":[240.0524697],"iteration":93,"passed_time":0.3189679961,"remaining_time":3.074308558},
{"learn":[236.4511966],"iteration":94,"passed_time":0.3199304615,"remaining_time":3.047758607},
{"learn":[233.1806635],"iteration":95,"passed_time":0.320918173,"remaining_time":3.021979463},
{"learn":[229.2022276],"iteration":96,"passed_time":0.3218995234,"remaining_time":2.996652264},
{"learn":[226.2835445],"iteration":97,"passed_time":0.322855471,"remaining_time":2.97158811},
{"learn":[224.2276542],"iteration":98,"passed_time":0.3238291176,"remaining_time":2.94717207},
{"learn":[221.0623352],"iteration":99,"passed_time":0.3247884826,"remaining_time":2.923096343},
{"learn":[218.1762626],"iteration":100,"passed_time":0.3257794188,"remaining_time":2.899759381},
{"learn":[215.3835243],"iteration":101,"passed_time":0.3269180187,"remaining_time":2.878160596},
{"learn":[212.1451547],"iteration":102,"passed_time":0.3287148272,"remaining_time":2.862691262},
{"learn":[209.3601737],"iteration":103,"passed_time":0.3300833643,"remaining_time":2.843795139},
{"learn":[206.7181097],"iteration":104,"passed_time":0.3311162517,"remaining_time":2.82237186},
{"learn":[203.6044035],"iteration":105,"passed_time":0.3321836813,"remaining_time":2.801624633},
{"learn":[200.8984104],"iteration":106,"passed_time":0.3332271165,"remaining_time":2.781045},
{"learn":[198.5618874],"iteration":107,"passed_time":0.3342905382,"remaining_time":2.760992223},
{"learn":[196.1027025],"iteration":108,"passed_time":0.335356528,"remaining_time":2.741308866},
{"learn":[194.3027831],"iteration":109,"passed_time":0.3363546451,"remaining_time":2.721414856},
{"learn":[192.2340166],"iteration":110,"passed_time":0.3373997373,"remaining_time":2.702237536},
{"learn":[190.0968298],"iteration":111,"passed_time":0.3383769048,"remaining_time":2.682845459},
{"learn":[187.903692],"iteration":112,"passed_time":0.339337805,"remaining_time":2.66365162},
{"learn":[186.6940649],"iteration":113,"passed_time":0.3402997442,"remaining_time":2.644785731},
{"learn":[184.8263221],"iteration":114,"passed_time":0.3418076066,"remaining_time":2.630432451},
{"learn":[183.0496073],"iteration":115,"passed_time":0.3434563904,"remaining_time":2.617374561},
{"learn":[180.8975709],"iteration":116,"passed_time":0.3452600128,"remaining_time":2.605680268},
{"learn":[179.5823627],"iteration":117,"passed_time":0.3462864574,"remaining_time":2.588344537},
{"learn":[177.9583391],"iteration":118,"passed_time":0.3472870463,"remaining_time":2.571091494},
{"learn":[176.0179979],"iteration":119,"passed_time":0.3482787814,"remaining_time":2.554044397},
{"learn":[174.0964689],"iteration":120,"passed_time":0.3492677947,"remaining_time":2.537242905},
{"learn":[172.1422434],"iteration":121,"passed_time":0.3502277359,"remaining_time":2.520491411},
{"learn":[170.578822],"iteration":122,"passed_time":0.3511991268,"remaining_time":2.504078327},
{"learn":[168.748726],"iteration":123,"passed_time":0.3521927412,"remaining_time":2.488071301},
{"learn":[167.6732717],"iteration":124,"passed_time":0.3532010096,"remaining_time":2.472407067},
{"learn":[166.6107604],"iteration":125,"passed_time":0.3541665339,"remaining_time":2.456678973},
{"learn":[165.0170873],"iteration":126,"passed_time":0.3551261532,"remaining_time":2.441142769},
{"learn":[163.3865047],"iteration":127,"passed_time":0.3565646198,"remaining_time":2.429096472},
{"learn":[161.7075759],"iteration":128,"passed_time":0.3590013107,"remaining_time":2.423954586},
{"learn":[160.1633484],"iteration":129,"passed_time":0.361169062,"remaining_time":2.417054492},
{"learn":[158.95065],"iteration":130,"passed_time":0.3631189409,"remaining_time":2.408781371},
{"learn":[157.4770131],"iteration":131,"passed_time":0.3643522527,"remaining_time":2.395892086},
{"learn":[156.6975298],"iteration":132,"passed_time":0.3655990247,"remaining_time":2.383265823},
{"learn":[155.3741227],"iteration":133,"passed_time":0.3666638099,"remaining_time":2.369633279},
{"learn":[154.0355908],"iteration":134,"passed_time":0.367780976,"remaining_time":2.35652255},
{"learn":[152.8983693],"iteration":135,"passed_time":0.3688678179,"remaining_time":2.343395549},
{"learn":[151.517726],"iteration":136,"passed_time":0.3698590786,"remaining_time":2.329842225},
{"learn":[150.3853082],"iteration":137,"passed_time":0.3710006681,"remaining_time":2.31740997},
{"learn":[149.0555771],"iteration":138,"passed_time":0.3720312764,"remaining_time":2.304452726},
{"learn":[147.8421936],"iteration":139,"passed_time":0.3735904865,"remaining_time":2.294912988},
{"learn":[146.8051449],"iteration":140,"passed_time":0.3748720717,"remaining_time":2.283795104},
{"learn":[145.5724501],"iteration":141,"passed_time":0.3759462714,"remaining_time":2.271562682},
{"learn":[144.7776695],"iteration":142,"passed_time":0.376984867,"remaining_time":2.259272944},
{"learn":[144.0881249],"iteration":143,"passed_time":0.3780544259,"remaining_time":2.247323532},
{"learn":[143.3029584],"iteration":144,"passed_time":0.3790910918,"remaining_time":2.235330231},
{"learn":[142.4831607],"iteration":145,"passed_time":0.380130583,"remaining_time":2.223503547},
{"learn":[141.6077433],"iteration":146,"passed_time":0.3811492095,"remaining_time":2.211702556},
{"learn":[140.7096828],"iteration":147,"passed_time":0.3821804774,"remaining_time":2.200120046},
{"learn":[139.8855049],"iteration":148,"passed_time":0.3831588165,"remaining_time":2.188376865},
{"learn":[139.2865191],"iteration":149,"passed_time":0.3843517696,"remaining_time":2.177993361},
{"learn":[138.4234229],"iteration":150,"passed_time":0.385683844,"remaining_time":2.168513799},
{"learn":[137.337729],"iteration":151,"passed_time":0.3868592639,"remaining_time":2.158267473},
{"learn":[136.5762193],"iteration":152,"passed_time":0.3894375972,"remaining_time":2.155906175},
{"learn":[135.4836064],"iteration":153,"passed_time":0.3913585299,"remaining_time":2.149930625},
{"learn":[134.5875012],"iteration":154,"passed_time":0.3933782536,"remaining_time":2.144545963},
{"learn":[133.8418645],"iteration":155,"passed_time":0.3950670279,"remaining_time":2.13741392},
{"learn":[132.8568653],"iteration":156,"passed_time":0.3960484759,"remaining_time":2.126553281},
{"learn":[132.0265163],"iteration":157,"passed_time":0.3970099548,"remaining_time":2.115711278},
{"learn":[131.2892015],"iteration":158,"passed_time":0.3979764389,"remaining_time":2.105020032},
{"learn":[130.5781046],"iteration":159,"passed_time":0.3993338303,"remaining_time":2.096502609},
{"learn":[129.7890103],"iteration":160,"passed_time":0.4005840435,"remaining_time":2.087515606},
{"learn":[129.0007968],"iteration":161,"passed_time":0.4018301722,"remaining_time":2.07860299},
{"learn":[128.1029514],"iteration":162,"passed_time":0.4035870677,"remaining_time":2.072407213},
{"learn":[127.3295823],"iteration":163,"passed_time":0.4060499524,"remaining_time":2.069864392},
{"learn":[126.7788773],"iteration":164,"passed_time":0.4075042601,"remaining_time":2.062218529},
{"learn":[126.0790212],"iteration":165,"passed_time":0.4086215751,"remaining_time":2.052954179},
{"learn":[125.3783357],"iteration":166,"passed_time":0.4095776086,"remaining_time":2.042982922},
{"learn":[124.7559847],"iteration":167,"passed_time":0.4105955826,"remaining_time":2.033425742},
{"learn":[123.9554371],"iteration":168,"passed_time":0.4115773566,"remaining_time":2.023791617},
{"learn":[123.3953694],"iteration":169,"passed_time":0.4125369692,"remaining_time":2.014151085},
{"learn":[122.8584934],"iteration":170,"passed_time":0.4135164583,"remaining_time":2.004708444},
{"learn":[122.2314739],"iteration":171,"passed_time":0.4145073061,"remaining_time":1.995418892},
{"learn":[121.439101],"iteration":172,"passed_time":0.4155075727,"remaining_time":1.986270304},
{"learn":[120.4683097],"iteration":173,"passed_time":0.4165028237,"remaining_time":1.977191565},
{"learn":[119.9029628],"iteration":174,"passed_time":0.4175251228,"remaining_time":1.968332722},
{"learn":[119.3481256],"iteration":175,"passed_time":0.4189632583,"remaining_time":1.9615098},
{"learn":[118.8374475],"iteration":176,"passed_time":0.4206808829,"remaining_time":1.956047269},
{"learn":[118.3374901],"iteration":177,"passed_time":0.4219119048,"remaining_time":1.948379695},
{"learn":[117.6566625],"iteration":178,"passed_time":0.4229003376,"remaining_time":1.939671381},
{"learn":[117.2343819],"iteration":179,"passed_time":0.4238668334,"remaining_time":1.930948908},
{"learn":[116.5725816],"iteration":180,"passed_time":0.424878159,"remaining_time":1.922514985},
{"learn":[116.0690588],"iteration":181,"passed_time":0.4258343776,"remaining_time":1.91391495},
{"learn":[115.4188406],"iteration":182,"passed_time":0.4268050905,"remaining_time":1.905463164},
{"learn":[115.1688396],"iteration":183,"passed_time":0.4277839483,"remaining_time":1.897128814},
{"learn":[114.6393111],"iteration":184,"passed_time":0.4287892492,"remaining_time":1.888990476},
{"learn":[114.0514857],"iteration":185,"passed_time":0.4297762969,"remaining_time":1.880848955},
{"learn":[113.5854189],"iteration":186,"passed_time":0.4307436283,"remaining_time":1.872698234},
{"learn":[113.1727585],"iteration":187,"passed_time":0.4317150667,"remaining_time":1.864641671},
{"learn":[112.7184611],"iteration":188,"passed_time":0.4327355154,"remaining_time":1.856870386},
{"learn":[111.9955348],"iteration":189,"passed_time":0.4340294026,"remaining_time":1.850335874},
{"learn":[111.2252065],"iteration":190,"passed_time":0.4356106598,"remaining_time":1.845073423},
{"learn":[110.6696821],"iteration":191,"passed_time":0.4368089946,"remaining_time":1.838237852},
{"learn":[110.0980313],"iteration":192,"passed_time":0.4377933521,"remaining_time":1.830565985},
{"learn":[109.4943173],"iteration":193,"passed_time":0.438772139,"remaining_time":1.822939918},
{"learn":[109.1668164],"iteration":194,"passed_time":0.4397263028,"remaining_time":1.815280378},
{"learn":[108.2007929],"iteration":195,"passed_time":0.4407282343,"remaining_time":1.807885206},
{"learn":[107.8170341],"iteration":196,"passed_time":0.4417094879,"remaining_time":1.800470654},
{"learn":[107.5727088],"iteration":197,"passed_time":0.4427372805,"remaining_time":1.793309591},
{"learn":[106.9795007],"iteration":198,"passed_time":0.4437151885,"remaining_time":1.786009377},
{"learn":[106.1198885],"iteration":199,"passed_time":0.4447006892,"remaining_time":1.778802757},
{"learn":[105.5891257],"iteration":200,"passed_time":0.445674782,"remaining_time":1.771612691},
{"learn":[104.7896663],"iteration":201,"passed_time":0.4466797657,"remaining_time":1.764606203},
{"learn":[104.1359134],"iteration":202,"passed_time":0.4476885144,"remaining_time":1.757673626},
{"learn":[103.456403],"iteration":203,"passed_time":0.4486877707,"remaining_time":1.750762086},
{"learn":[102.9377854],"iteration":204,"passed_time":0.4501746926,"remaining_time":1.745799418},
{"learn":[102.4766826],"iteration":205,"passed_time":0.4515087572,"remaining_time":1.740281326},
{"learn":[102.1803782],"iteration":206,"passed_time":0.452606503,"remaining_time":1.733898342},
{"learn":[101.8733122],"iteration":207,"passed_time":0.4535728378,"remaining_time":1.727065806},
{"learn":[101.5078204],"iteration":208,"passed_time":0.4545581343,"remaining_time":1.720361169},
{"learn":[100.9342579],"iteration":209,"passed_time":0.4555337069,"remaining_time":1.713674421},
{"learn":[100.3780172],"iteration":210,"passed_time":0.4565195896,"remaining_time":1.707080361},
{"learn":[100.0142594],"iteration":211,"passed_time":0.4581435293,"remaining_time":1.702910854},
{"learn":[99.1999133],"iteration":212,"passed_time":0.4592511458,"remaining_time":1.69685752},
{"learn":[98.89974964],"iteration":213,"passed_time":0.4604379587,"remaining_time":1.691141288},
{"learn":[98.33758747],"iteration":214,"passed_time":0.4615296749,"remaining_time":1.685119976},
{"learn":[97.59423509],"iteration":215,"passed_time":0.4625040237,"remaining_time":1.678718308},
{"learn":[97.19114582],"iteration":216,"passed_time":0.4634681553,"remaining_time":1.672329795},
{"learn":[96.89616225],"iteration":217,"passed_time":0.4651110349,"remaining_time":1.668425823},
{"learn":[96.70222809],"iteration":218,"passed_time":0.4664639786,"remaining_time":1.663508526},
{"learn":[96.20572347],"iteration":219,"passed_time":0.4675685713,"remaining_time":1.657743116},
{"learn":[95.76492625],"iteration":220,"passed_time":0.4685977227,"remaining_time":1.651753964},
{"learn":[95.54670396],"iteration":221,"passed_time":0.4696533611,"remaining_time":1.645902319},
{"learn":[95.36704006],"iteration":222,"passed_time":0.4706983119,"remaining_time":1.64005645},
{"learn":[94.95616849],"iteration":223,"passed_time":0.4718320897,"remaining_time":1.634561168},
{"learn":[94.255013],"iteration":224,"passed_time":0.4728419634,"remaining_time":1.628677874},
{"learn":[93.67168999],"iteration":225,"passed_time":0.4739210278,"remaining_time":1.62307467},
{"learn":[93.36311047],"iteration":226,"passed_time":0.4750597465,"remaining_time":1.617714467},
{"learn":[93.09967774],"iteration":227,"passed_time":0.4760878222,"remaining_time":1.612016661},
{"learn":[92.4950885],"iteration":228,"passed_time":0.4771315326,"remaining_time":1.606412278},
{"learn":[92.27301979],"iteration":229,"passed_time":0.4781429186,"remaining_time":1.600739336},
{"learn":[91.98875347],"iteration":230,"passed_time":0.4791423125,"remaining_time":1.595066833},
{"learn":[91.59059286],"iteration":231,"passed_time":0.4804596625,"remaining_time":1.590487158},
{"learn":[91.40459135],"iteration":232,"passed_time":0.4814398895,"remaining_time":1.584825731},
{"learn":[90.9108101],"iteration":233,"passed_time":0.4827122792,"remaining_time":1.580160709},
{"learn":[90.45225606],"iteration":234,"passed_time":0.4838832468,"remaining_time":1.575194399},
{"learn":[89.86302319],"iteration":235,"passed_time":0.4849864068,"remaining_time":1.570040741},
{"learn":[89.70136443],"iteration":236,"passed_time":0.4861036105,"remaining_time":1.564966476},
{"learn":[89.10601809],"iteration":237,"passed_time":0.4872191087,"remaining_time":1.559920004},
{"learn":[88.8258042],"iteration":238,"passed_time":0.4884167255,"remaining_time":1.5551679},
{"learn":[88.21738488],"iteration":239,"passed_time":0.4896911941,"remaining_time":1.550688781},
{"learn":[88.04570075],"iteration":240,"passed_time":0.4910940398,"remaining_time":1.546640565},
{"learn":[87.84101065],"iteration":241,"passed_time":0.492218333,"remaining_time":1.541741721},
{"learn":[87.36732643],"iteration":242,"passed_time":0.4935912299,"remaining_time":1.537648399},
{"learn":[86.79699335],"iteration":243,"passed_time":0.4949508845,"remaining_time":1.533536347},
{"learn":[86.63802992],"iteration":244,"passed_time":0.4961993015,"remaining_time":1.52910397},
{"learn":[86.48304517],"iteration":245,"passed_time":0.4972820255,"remaining_time":1.524189623},
{"learn":[86.37163845],"iteration":246,"passed_time":0.4985421928,"remaining_time":1.519847252},
{"learn":[85.89984853],"iteration":247,"passed_time":0.4997218194,"remaining_time":1.515285517},
{"learn":[85.51927328],"iteration":248,"passed_time":0.5009598195,"remaining_time":1.510927006},
{"learn":[85.36993473],"iteration":249,"passed_time":0.5020823544,"remaining_time":1.506247063},
{"learn":[85.15525216],"iteration":250,"passed_time":0.5041402399,"remaining_time":1.504386612},
{"learn":[84.8007438],"iteration":251,"passed_time":0.5061095632,"remaining_time":1.502261719},
{"learn":[84.68831722],"iteration":252,"passed_time":0.5071094199,"remaining_time":1.497275639},
{"learn":[84.36916663],"iteration":253,"passed_time":0.5080952568,"remaining_time":1.49227977},
{"learn":[84.0414804],"iteration":254,"passed_time":0.5090511926,"remaining_time":1.487227994},
{"learn":[83.73335914],"iteration":255,"passed_time":0.5106017654,"remaining_time":1.483936381},
{"learn":[83.23894975],"iteration":256,"passed_time":0.5129416138,"remaining_time":1.482940152},
{"learn":[82.84941844],"iteration":257,"passed_time":0.5140428045,"remaining_time":1.478371166},
{"learn":[82.51518108],"iteration":258,"passed_time":0.5150281602,"remaining_time":1.473497555},
{"learn":[82.03294204],"iteration":259,"passed_time":0.5160711409,"remaining_time":1.468817863},
{"learn":[81.57999702],"iteration":260,"passed_time":0.5170422741,"remaining_time":1.463962608},
{"learn":[81.25641148],"iteration":261,"passed_time":0.5180333847,"remaining_time":1.459193274},
{"learn":[80.80804897],"iteration":262,"passed_time":0.519016618,"remaining_time":1.454430599},
{"learn":[80.50644405],"iteration":263,"passed_time":0.5199668724,"remaining_time":1.449604614},
{"learn":[80.06765866],"iteration":264,"passed_time":0.5209401989,"remaining_time":1.444871872},
{"learn":[79.97700689],"iteration":265,"passed_time":0.5218956502,"remaining_time":1.440118072},
{"learn":[79.88147971],"iteration":266,"passed_time":0.5228187197,"remaining_time":1.435303826},
{"learn":[79.46174868],"iteration":267,"passed_time":0.5238188424,"remaining_time":1.430729077},
{"learn":[79.17696702],"iteration":268,"passed_time":0.5249701392,"remaining_time":1.426591716},
{"learn":[78.87722908],"iteration":269,"passed_time":0.5271042031,"remaining_time":1.425133586},
{"learn":[78.51492013],"iteration":270,"passed_time":0.5285473267,"remaining_time":1.421811812},
{"learn":[78.31182201],"iteration":271,"passed_time":0.5295228864,"remaining_time":1.417252431},
{"learn":[78.0692521],"iteration":272,"passed_time":0.5305224779,"remaining_time":1.412783302},
{"learn":[77.78258302],"iteration":273,"passed_time":0.5315471111,"remaining_time":1.408405849},
{"learn":[77.567296],"iteration":274,"passed_time":0.532517011,"remaining_time":1.403908483},
{"learn":[77.26362773],"iteration":275,"passed_time":0.5335217653,"remaining_time":1.399528109},
{"learn":[77.06493324],"iteration":276,"passed_time":0.534510294,"remaining_time":1.395129757},
{"learn":[76.9613506],"iteration":277,"passed_time":0.5354389491,"remaining_time":1.390600436},
{"learn":[76.70264403],"iteration":278,"passed_time":0.5364510269,"remaining_time":1.38631251},
{"learn":[76.54344625],"iteration":279,"passed_time":0.5374151343,"remaining_time":1.381924631},
{"learn":[76.32276122],"iteration":280,"passed_time":0.538481027,"remaining_time":1.37782156},
{"learn":[76.02808101],"iteration":281,"passed_time":0.5398408963,"remaining_time":1.374488523},
{"learn":[75.64068316],"iteration":282,"passed_time":0.5425539428,"remaining_time":1.374597799},
{"learn":[75.54438431],"iteration":283,"passed_time":0.5440650079,"remaining_time":1.371656851},
{"learn":[75.35510359],"iteration":284,"passed_time":0.5451072593,"remaining_time":1.367549791},
{"learn":[75.09197279],"iteration":285,"passed_time":0.5461581277,"remaining_time":1.363485675},
{"learn":[74.74875667],"iteration":286,"passed_time":0.5474422455,"remaining_time":1.360022025},
{"learn":[74.353068],"iteration":287,"passed_time":0.5484369945,"remaining_time":1.355858125},
{"learn":[74.02644719],"iteration":288,"passed_time":0.5493850198,"remaining_time":1.351601208},
{"learn":[73.8062053],"iteration":289,"passed_time":0.5503417838,"remaining_time":1.347388505},
{"learn":[73.60580737],"iteration":290,"passed_time":0.551310592,"remaining_time":1.343227525},
{"learn":[73.27991577],"iteration":291,"passed_time":0.5522952606,"remaining_time":1.339126865},
{"learn":[72.88517711],"iteration":292,"passed_time":0.5534534759,"remaining_time":1.335466237},
{"learn":[72.48561363],"iteration":293,"passed_time":0.5546271483,"remaining_time":1.331859751},
{"learn":[72.42037253],"iteration":294,"passed_time":0.556910151,"remaining_time":1.330920869},
{"learn":[72.01886335],"iteration":295,"passed_time":0.5589283052,"remaining_time":1.329342996},
{"learn":[71.70823937],"iteration":296,"passed_time":0.5602397293,"remaining_time":1.326089326},
{"learn":[71.42205093],"iteration":297,"passed_time":0.5612572643,"remaining_time":1.322156374},
{"learn":[71.10407239],"iteration":298,"passed_time":0.5622283445,"remaining_time":1.318134012},
{"learn":[70.82368652],"iteration":299,"passed_time":0.5632078453,"remaining_time":1.314151639},
{"learn":[70.77420802],"iteration":300,"passed_time":0.5641537291,"remaining_time":1.310111152},
{"learn":[70.5914929],"iteration":301,"passed_time":0.5651402439,"remaining_time":1.306185067},
{"learn":[70.37787859],"iteration":302,"passed_time":0.5661153278,"remaining_time":1.302252091},
{"learn":[70.3219184],"iteration":303,"passed_time":0.5671593476,"remaining_time":1.298496401},
{"learn":[70.08045108],"iteration":304,"passed_time":0.5681860994,"remaining_time":1.294719145},
{"learn":[69.84178424],"iteration":305,"passed_time":0.5692395488,"remaining_time":1.291020415},
{"learn":[69.64284737],"iteration":306,"passed_time":0.5702446575,"remaining_time":1.287229797},
{"learn":[69.5726849],"iteration":307,"passed_time":0.5717991184,"remaining_time":1.284691526},
{"learn":[69.38397463],"iteration":308,"passed_time":0.5730717461,"remaining_time":1.281529374},
{"learn":[69.2241088],"iteration":309,"passed_time":0.5741569302,"remaining_time":1.277962199},
{"learn":[68.86562363],"iteration":310,"passed_time":0.5752981048,"remaining_time":1.27453503},
{"learn":[68.62877088],"iteration":311,"passed_time":0.576371318,"remaining_time":1.27097265},
{"learn":[68.41135072],"iteration":312,"passed_time":0.5773574926,"remaining_time":1.267235136},
{"learn":[68.05938097],"iteration":313,"passed_time":0.5783887872,"remaining_time":1.26361372},
{"learn":[67.82692452],"iteration":314,"passed_time":0.5793463826,"remaining_time":1.259848483},
{"learn":[67.61208637],"iteration":315,"passed_time":0.5803248601,"remaining_time":1.256146216},
{"learn":[67.41155886],"iteration":316,"passed_time":0.5813773417,"remaining_time":1.252620582},
{"learn":[67.26216989],"iteration":317,"passed_time":0.5824976988,"remaining_time":1.249256071},
{"learn":[66.94703986],"iteration":318,"passed_time":0.5834861433,"remaining_time":1.245624024},
{"learn":[66.70578648],"iteration":319,"passed_time":0.5844935186,"remaining_time":1.242048727},
{"learn":[66.59854719],"iteration":320,"passed_time":0.5855018863,"remaining_time":1.238491529},
{"learn":[66.38024081],"iteration":321,"passed_time":0.5868001808,"remaining_time":1.235560629},
{"learn":[66.102133],"iteration":322,"passed_time":0.5878015652,"remaining_time":1.232017522},
{"learn":[65.94759432],"iteration":323,"passed_time":0.5887890657,"remaining_time":1.228461137},
{"learn":[65.69920695],"iteration":324,"passed_time":0.5898629536,"remaining_time":1.22509998},
{"learn":[65.45612607],"iteration":325,"passed_time":0.5908583104,"remaining_time":1.221590495},
{"learn":[65.18977723],"iteration":326,"passed_time":0.5919137128,"remaining_time":1.218219965},
{"learn":[64.97991245],"iteration":327,"passed_time":0.5929629275,"remaining_time":1.214850876},
{"learn":[64.80436188],"iteration":328,"passed_time":0.5939714252,"remaining_time":1.211412846},
{"learn":[64.67703423],"iteration":329,"passed_time":0.5949958525,"remaining_time":1.208021882},
{"learn":[64.53242712],"iteration":330,"passed_time":0.5960063125,"remaining_time":1.204616988},
{"learn":[64.39028019],"iteration":331,"passed_time":0.597118247,"remaining_time":1.20143069},
{"learn":[64.20016617],"iteration":332,"passed_time":0.5981588248,"remaining_time":1.198113922},
{"learn":[63.99165004],"iteration":333,"passed_time":0.5991952159,"remaining_time":1.194802436},
{"learn":[63.95643117],"iteration":334,"passed_time":0.6002301672,"remaining_time":1.191501675},
{"learn":[63.78795288],"iteration":335,"passed_time":0.6012840593,"remaining_time":1.188251832},
{"learn":[63.59920328],"iteration":336,"passed_time":0.6024974605,"remaining_time":1.185328832},
{"learn":[63.33365897],"iteration":337,"passed_time":0.6035005144,"remaining_time":1.182003966},
{"learn":[63.15952971],"iteration":338,"passed_time":0.6044909036,"remaining_time":1.178668104},
{"learn":[62.97992811],"iteration":339,"passed_time":0.6054580899,"remaining_time":1.175300998},
{"learn":[62.79347999],"iteration":340,"passed_time":0.606434064,"remaining_time":1.171964951},
{"learn":[62.5345418],"iteration":341,"passed_time":0.6073847137,"remaining_time":1.168593981},
{"learn":[62.3195096],"iteration":342,"passed_time":0.6084100182,"remaining_time":1.165380122},
{"learn":[62.14717993],"iteration":343,"passed_time":0.6093858623,"remaining_time":1.162084668},
{"learn":[62.02883244],"iteration":344,"passed_time":0.6103937062,"remaining_time":1.158863413},
{"learn":[61.75418348],"iteration":345,"passed_time":0.6114017403,"remaining_time":1.155655313},
{"learn":[61.50259373],"iteration":346,"passed_time":0.6124005355,"remaining_time":1.152442506},
{"learn":[61.39712193],"iteration":347,"passed_time":0.6134045643,"remaining_time":1.14925223},
{"learn":[61.29614135],"iteration":348,"passed_time":0.6144044768,"remaining_time":1.146066803},
{"learn":[61.11245729],"iteration":349,"passed_time":0.6154511289,"remaining_time":1.142980668},
{"learn":[60.96559726],"iteration":350,"passed_time":0.6167031434,"remaining_time":1.140285869},
{"learn":[60.7552434],"iteration":351,"passed_time":0.6177389787,"remaining_time":1.137201302},
{"learn":[60.55238608],"iteration":352,"passed_time":0.6187373702,"remaining_time":1.134059712},
{"learn":[60.36229725],"iteration":353,"passed_time":0.6197592907,"remaining_time":1.130973169},
{"learn":[60.20928134],"iteration":354,"passed_time":0.6207204944,"remaining_time":1.127787941},
{"learn":[60.09810265],"iteration":355,"passed_time":0.6216764011,"remaining_time":1.124605624},
{"learn":[59.88847696],"iteration":356,"passed_time":0.6226350289,"remaining_time":1.121440682},
{"learn":[59.7771898],"iteration":357,"passed_time":0.6236117935,"remaining_time":1.118320591},
{"learn":[59.74736247],"iteration":358,"passed_time":0.6245266097,"remaining_time":1.11510183},
{"learn":[59.56504174],"iteration":359,"passed_time":0.6255460335,"remaining_time":1.112081837},
{"learn":[59.39882181],"iteration":360,"passed_time":0.6265302993,"remaining_time":1.109010696},
{"learn":[59.2593189],"iteration":361,"passed_time":0.6274886535,"remaining_time":1.105905417},
{"learn":[59.10108315],"iteration":362,"passed_time":0.6284526475,"remaining_time":1.102821864},
{"learn":[58.96509167],"iteration":363,"passed_time":0.6294477359,"remaining_time":1.099804286},
{"learn":[58.93529499],"iteration":364,"passed_time":0.6303900514,"remaining_time":1.09670598},
{"learn":[58.67618266],"iteration":365,"passed_time":0.6313939526,"remaining_time":1.093726136},
{"learn":[58.51104458],"iteration":366,"passed_time":0.6323717029,"remaining_time":1.090711956},
{"learn":[58.34090265],"iteration":367,"passed_time":0.6333454038,"remaining_time":1.087701889},
{"learn":[58.14903442],"iteration":368,"passed_time":0.6343422271,"remaining_time":1.084742399},
{"learn":[58.00908844],"iteration":369,"passed_time":0.6352948565,"remaining_time":1.081718269},
{"learn":[57.78541274],"iteration":370,"passed_time":0.6362662707,"remaining_time":1.078737154},
{"learn":[57.62490913],"iteration":371,"passed_time":0.6371999401,"remaining_time":1.075703125},
{"learn":[57.50342146],"iteration":372,"passed_time":0.638183146,"remaining_time":1.072763626},
{"learn":[57.31297999],"iteration":373,"passed_time":0.6391785721,"remaining_time":1.069855043},
{"learn":[57.11666483],"iteration":374,"passed_time":0.6401563917,"remaining_time":1.066927319},
{"learn":[56.91207688],"iteration":375,"passed_time":0.6411249389,"remaining_time":1.063994579},
{"learn":[56.76888392],"iteration":376,"passed_time":0.64209897,"remaining_time":1.061081322},
{"learn":[56.69155225],"iteration":377,"passed_time":0.6430518454,"remaining_time":1.058143513},
{"learn":[56.57307881],"iteration":378,"passed_time":0.6441467538,"remaining_time":1.055448903},
{"learn":[56.40958964],"iteration":379,"passed_time":0.6451507029,"remaining_time":1.052614305},
{"learn":[56.20791784],"iteration":380,"passed_time":0.646110991,"remaining_time":1.049718382},
{"learn":[56.01775213],"iteration":381,"passed_time":0.6473588597,"remaining_time":1.047297841},
{"learn":[55.89641853],"iteration":382,"passed_time":0.6483428719,"remaining_time":1.04445836},
{"learn":[55.66043999],"iteration":383,"passed_time":0.6493153761,"remaining_time":1.041610083},
{"learn":[55.50068627],"iteration":384,"passed_time":0.6502815842,"remaining_time":1.038761492},
{"learn":[55.3046999],"iteration":385,"passed_time":0.6512940681,"remaining_time":1.035996264},
{"learn":[55.12791262],"iteration":386,"passed_time":0.6522463764,"remaining_time":1.033144777},
{"learn":[54.97360457],"iteration":387,"passed_time":0.6531918241,"remaining_time":1.030292259},
{"learn":[54.83305444],"iteration":388,"passed_time":0.6541558582,"remaining_time":1.027478739},
{"learn":[54.73404399],"iteration":389,"passed_time":0.6551006662,"remaining_time":1.024644632},
{"learn":[54.61416756],"iteration":390,"passed_time":0.6561191206,"remaining_time":1.021934896},
{"learn":[54.44237505],"iteration":391,"passed_time":0.6570697402,"remaining_time":1.019128577},
{"learn":[54.2624505],"iteration":392,"passed_time":0.6581240735,"remaining_time":1.01649189},
{"learn":[54.09022696],"iteration":393,"passed_time":0.6591313162,"remaining_time":1.013790806},
{"learn":[53.92376648],"iteration":394,"passed_time":0.6602490481,"remaining_time":1.011267529},
{"learn":[53.80729591],"iteration":395,"passed_time":0.661267146,"remaining_time":1.008599384},
{"learn":[53.65721975],"iteration":396,"passed_time":0.662241893,"remaining_time":1.005873706},
{"learn":[53.49737932],"iteration":397,"passed_time":0.6632922243,"remaining_time":1.003271153},
{"learn":[53.32643209],"iteration":398,"passed_time":0.6642554644,"remaining_time":1.000545198},
{"learn":[53.19050636],"iteration":399,"passed_time":0.6652312759,"remaining_time":0.9978469139},
{"learn":[53.00205604],"iteration":400,"passed_time":0.6661635635,"remaining_time":0.9950922059},
{"learn":[52.84942603],"iteration":401,"passed_time":0.6671413181,"remaining_time":0.9924141995},
{"learn":[52.64557651],"iteration":402,"passed_time":0.6681416901,"remaining_time":0.9897781365},
{"learn":[52.50206033],"iteration":403,"passed_time":0.6690916476,"remaining_time":0.987075797},
{"learn":[52.41650477],"iteration":404,"passed_time":0.6700671085,"remaining_time":0.9844195791},
{"learn":[52.26930937],"iteration":405,"passed_time":0.6710301135,"remaining_time":0.9817534173},
{"learn":[52.16626298],"iteration":406,"passed_time":0.6719696804,"remaining_time":0.9790614753},
{"learn":[51.99341628],"iteration":407,"passed_time":0.6730559423,"remaining_time":0.9765909751},
{"learn":[51.8821798],"iteration":408,"passed_time":0.6740297632,"remaining_time":0.9739647679},
{"learn":[51.73120988],"iteration":409,"passed_time":0.6750636375,"remaining_time":0.9714330394},
{"learn":[51.58599282],"iteration":410,"passed_time":0.6760880031,"remaining_time":0.9688949728},
{"learn":[51.43523561],"iteration":411,"passed_time":0.6770364938,"remaining_time":0.9662559668},
{"learn":[51.27131861],"iteration":412,"passed_time":0.6781661762,"remaining_time":0.9638826765},
{"learn":[51.11005019],"iteration":413,"passed_time":0.6791783273,"remaining_time":0.9613490334},
{"learn":[50.94620003],"iteration":414,"passed_time":0.6801799111,"remaining_time":0.9588078264},
{"learn":[50.8506684],"iteration":415,"passed_time":0.6811576406,"remaining_time":0.9562405339},
{"learn":[50.73337818],"iteration":416,"passed_time":0.6821881613,"remaining_time":0.9537546716},
{"learn":[50.55063207],"iteration":417,"passed_time":0.6831714897,"remaining_time":0.9512100647},
{"learn":[50.40019996],"iteration":418,"passed_time":0.6842143024,"remaining_time":0.9487553931},
{"learn":[50.30349619],"iteration":419,"passed_time":0.6852499301,"remaining_time":0.9462975225},
{"learn":[50.15322261],"iteration":420,"passed_time":0.6862596729,"remaining_time":0.943810809},
{"learn":[50.05755541],"iteration":421,"passed_time":0.6873501507,"remaining_time":0.9414416755},
{"learn":[49.87012231],"iteration":422,"passed_time":0.6884280938,"remaining_time":0.9390614897},
{"learn":[49.77050381],"iteration":423,"passed_time":0.6895443176,"remaining_time":0.9367394503},
{"learn":[49.67450548],"iteration":424,"passed_time":0.6906356418,"remaining_time":0.9343893978},
{"learn":[49.52915751],"iteration":425,"passed_time":0.6916906406,"remaining_time":0.9319963091},
{"learn":[49.40429197],"iteration":426,"passed_time":0.6927605977,"remaining_time":0.9296295609},
{"learn":[49.28341938],"iteration":427,"passed_time":0.6940981122,"remaining_time":0.927626449},
{"learn":[49.21585292],"iteration":428,"passed_time":0.6951262112,"remaining_time":0.9252146075},
{"learn":[49.13621904],"iteration":429,"passed_time":0.6960950128,"remaining_time":0.9227305984},
{"learn":[48.97160256],"iteration":430,"passed_time":0.6970706434,"remaining_time":0.9202626359},
{"learn":[48.80459068],"iteration":431,"passed_time":0.6980800726,"remaining_time":0.9178460214},
{"learn":[48.69090744],"iteration":432,"passed_time":0.6991229003,"remaining_time":0.9154796408},
{"learn":[48.61976373],"iteration":433,"passed_time":0.7001507658,"remaining_time":0.9130998467},
{"learn":[48.47284494],"iteration":434,"passed_time":0.7011591418,"remaining_time":0.9107009543},
{"learn":[48.38954986],"iteration":435,"passed_time":0.7023539245,"remaining_time":0.9085495721},
{"learn":[48.20168938],"iteration":436,"passed_time":0.7034677128,"remaining_time":0.9062982204},
{"learn":[48.052341],"iteration":437,"passed_time":0.7044985021,"remaining_time":0.9039455666},
{"learn":[47.93475623],"iteration":438,"passed_time":0.7055107083,"remaining_time":0.9015751876},
{"learn":[47.79054251],"iteration":439,"passed_time":0.706607257,"remaining_time":0.8993183271},
{"learn":[47.65928381],"iteration":440,"passed_time":0.7076582738,"remaining_time":0.8970090137},
{"learn":[47.50270985],"iteration":441,"passed_time":0.7089924176,"remaining_time":0.8950628258},
{"learn":[47.32548932],"iteration":442,"passed_time":0.710048919,"remaining_time":0.8927703113},
{"learn":[47.16108106],"iteration":443,"passed_time":0.7110796482,"remaining_time":0.890451091},
{"learn":[47.08502433],"iteration":444,"passed_time":0.7120803739,"remaining_time":0.8881002416},
{"learn":[46.96275099],"iteration":445,"passed_time":0.7131238178,"remaining_time":0.8858085091},
{"learn":[46.88372595],"iteration":446,"passed_time":0.7141296796,"remaining_time":0.8834758676},
{"learn":[46.75600013],"iteration":447,"passed_time":0.7151160735,"remaining_time":0.881125162},
{"learn":[46.64460522],"iteration":448,"passed_time":0.7161425326,"remaining_time":0.8788297004},
{"learn":[46.61962555],"iteration":449,"passed_time":0.7171206082,"remaining_time":0.8764807434},
{"learn":[46.51502774],"iteration":450,"passed_time":0.7181465123,"remaining_time":0.8741960871},
{"learn":[46.36983606],"iteration":451,"passed_time":0.719131758,"remaining_time":0.8718677066},
{"learn":[46.21266118],"iteration":452,"passed_time":0.7201035183,"remaining_time":0.8695289724},
{"learn":[46.04777694],"iteration":453,"passed_time":0.7210717019,"remaining_time":0.8671919587},
{"learn":[45.99774704],"iteration":454,"passed_time":0.7220456096,"remaining_time":0.8648678181},
{"learn":[45.84751821],"iteration":455,"passed_time":0.7230109862,"remaining_time":0.8625394222},
{"learn":[45.70627253],"iteration":456,"passed_time":0.7241291835,"remaining_time":0.8603985703},
{"learn":[45.58847234],"iteration":457,"passed_time":0.7251924785,"remaining_time":0.8581972125},
{"learn":[45.48903787],"iteration":458,"passed_time":0.7261652912,"remaining_time":0.8558941667},
{"learn":[45.38223728],"iteration":459,"passed_time":0.7271402454,"remaining_time":0.8535994185},
{"learn":[45.29324708],"iteration":460,"passed_time":0.7281583708,"remaining_time":0.8513608717},
{"learn":[45.19097708],"iteration":461,"passed_time":0.7291407569,"remaining_time":0.8490859896},
{"learn":[45.10733009],"iteration":462,"passed_time":0.7300745339,"remaining_time":0.8467603125},
{"learn":[44.96633408],"iteration":463,"passed_time":0.7312243667,"remaining_time":0.8446902167},
{"learn":[44.81926791],"iteration":464,"passed_time":0.7323295506,"remaining_time":0.8425727088},
{"learn":[44.73663394],"iteration":465,"passed_time":0.7334150245,"remaining_time":0.8404369594},
{"learn":[44.65105116],"iteration":466,"passed_time":0.7344799677,"remaining_time":0.8382822758},
{"learn":[44.58230454],"iteration":467,"passed_time":0.7355011552,"remaining_time":0.8360825098},
{"learn":[44.44432394],"iteration":468,"passed_time":0.7366077089,"remaining_time":0.8339844209},
{"learn":[44.32592356],"iteration":469,"passed_time":0.7377116282,"remaining_time":0.8318875807},
{"learn":[44.17230329],"iteration":470,"passed_time":0.7387834629,"remaining_time":0.8297589212},
{"learn":[44.07218721],"iteration":471,"passed_time":0.7401526179,"remaining_time":0.8279673353},
{"learn":[43.96684337],"iteration":472,"passed_time":0.7412353632,"remaining_time":0.825858428},
{"learn":[43.80345795],"iteration":473,"passed_time":0.7422376875,"remaining_time":0.8236646068},
{"learn":[43.68059382],"iteration":474,"passed_time":0.7432096196,"remaining_time":0.8214422111},
{"learn":[43.59958075],"iteration":475,"passed_time":0.7441858264,"remaining_time":0.8192297752},
{"learn":[43.49563718],"iteration":476,"passed_time":0.7454546739,"remaining_time":0.8173433846},
{"learn":[43.39608726],"iteration":477,"passed_time":0.7465469472,"remaining_time":0.8152667498},
{"learn":[43.27678574],"iteration":478,"passed_time":0.7475975862,"remaining_time":0.8131489403},
{"learn":[43.17781436],"iteration":479,"passed_time":0.7486203531,"remaining_time":0.8110053825},
{"learn":[43.08980638],"iteration":480,"passed_time":0.7496599319,"remaining_time":0.808884625},
{"learn":[42.97346477],"iteration":481,"passed_time":0.7506954357,"remaining_time":0.8067639744},
{"learn":[42.88609947],"iteration":482,"passed_time":0.7519210983,"remaining_time":0.804851362},
{"learn":[42.79382501],"iteration":483,"passed_time":0.7530556954,"remaining_time":0.8028445017},
{"learn":[42.69318243],"iteration":484,"passed_time":0.7542303294,"remaining_time":0.8008837518},
{"learn":[42.58585893],"iteration":485,"passed_time":0.7555716169,"remaining_time":0.799102492},
{"learn":[42.46537129],"iteration":486,"passed_time":0.7567021945,"remaining_time":0.7971010797},
{"learn":[42.42538006],"iteration":487,"passed_time":0.7577398632,"remaining_time":0.7950057581},
{"learn":[42.29511587],"iteration":488,"passed_time":0.758828699,"remaining_time":0.7929682315},
{"learn":[42.22794675],"iteration":489,"passed_time":0.7599187465,"remaining_time":0.7909358382},
{"learn":[42.09566688],"iteration":490,"passed_time":0.760994356,"remaining_time":0.7888923161},
{"learn":[42.04097458],"iteration":491,"passed_time":0.7621107294,"remaining_time":0.7868948182},
{"learn":[41.93083842],"iteration":492,"passed_time":0.7633111769,"remaining_time":0.7849873564},
{"learn":[41.83548959],"iteration":493,"passed_time":0.7644206981,"remaining_time":0.7829896219},
{"learn":[41.73033065],"iteration":494,"passed_time":0.7655471586,"remaining_time":0.7810127578},
{"learn":[41.65983245],"iteration":495,"passed_time":0.7666745673,"remaining_time":0.7790402862},
{"learn":[41.57139774],"iteration":496,"passed_time":0.7680322335,"remaining_time":0.7773042524},
{"learn":[41.47585099],"iteration":497,"passed_time":0.7692004533,"remaining_time":0.7753787702},
{"learn":[41.37268538],"iteration":498,"passed_time":0.7713277863,"remaining_time":0.7744192804},
{"learn":[41.30158566],"iteration":499,"passed_time":0.772522112,"remaining_time":0.772522112},
{"learn":[41.18023576],"iteration":500,"passed_time":0.7739978652,"remaining_time":0.7709080533},
{"learn":[41.15842698],"iteration":501,"passed_time":0.7755655329,"remaining_time":0.7693857278},
{"learn":[41.14026286],"iteration":502,"passed_time":0.7769748127,"remaining_time":0.7677067235},
{"learn":[41.06475453],"iteration":503,"passed_time":0.7782435727,"remaining_time":0.7658905002},
{"learn":[40.93947803],"iteration":504,"passed_time":0.7793188357,"remaining_time":0.7638867795},
{"learn":[40.85287623],"iteration":505,"passed_time":0.7803943989,"remaining_time":0.7618870218},
{"learn":[40.77963986],"iteration":506,"passed_time":0.7815055203,"remaining_time":0.7599254862},
{"learn":[40.68029976],"iteration":507,"passed_time":0.7826461804,"remaining_time":0.757995907},
{"learn":[40.58311287],"iteration":508,"passed_time":0.7838477191,"remaining_time":0.7561281534},
{"learn":[40.50695975],"iteration":509,"passed_time":0.7853124904,"remaining_time":0.7545159221},
{"learn":[40.40487327],"iteration":510,"passed_time":0.7864992224,"remaining_time":0.7526381991},
{"learn":[40.30796753],"iteration":511,"passed_time":0.7876202079,"remaining_time":0.7507005106},
{"learn":[40.25651679],"iteration":512,"passed_time":0.7888357063,"remaining_time":0.748855729},
{"learn":[40.15965437],"iteration":513,"passed_time":0.7903207577,"remaining_time":0.7472682651},
{"learn":[40.10238847],"iteration":514,"passed_time":0.7915654004,"remaining_time":0.7454547945},
{"learn":[39.99347019],"iteration":515,"passed_time":0.7928396471,"remaining_time":0.7436712969},
{"learn":[39.89214972],"iteration":516,"passed_time":0.7941191947,"remaining_time":0.7418947215},
{"learn":[39.80685972],"iteration":517,"passed_time":0.7952799064,"remaining_time":0.7400094882},
{"learn":[39.75196761],"iteration":518,"passed_time":0.7964047003,"remaining_time":0.7380937589},
{"learn":[39.65715533],"iteration":519,"passed_time":0.7975721576,"remaining_time":0.7362204531},
{"learn":[39.54635283],"iteration":520,"passed_time":0.798934944,"remaining_time":0.7345294399},
{"learn":[39.50226171],"iteration":521,"passed_time":0.8001042996,"remaining_time":0.7326625579},
{"learn":[39.37847471],"iteration":522,"passed_time":0.8017650043,"remaining_time":0.7312464762},
{"learn":[39.28902415],"iteration":523,"passed_time":0.803159347,"remaining_time":0.7295874984},
{"learn":[39.23887311],"iteration":524,"passed_time":0.8045545583,"remaining_time":0.7279303146},
{"learn":[39.16478713],"iteration":525,"passed_time":0.8060264863,"remaining_time":0.7263432595},
{"learn":[39.10772378],"iteration":526,"passed_time":0.807466682,"remaining_time":0.7247281605},
{"learn":[39.00758002],"iteration":527,"passed_time":0.8089581041,"remaining_time":0.7231595173},
{"learn":[38.91084369],"iteration":528,"passed_time":0.8102417487,"remaining_time":0.7214061694},
{"learn":[38.80218808],"iteration":529,"passed_time":0.8117207237,"remaining_time":0.7198278116},
{"learn":[38.76133453],"iteration":530,"passed_time":0.8129870091,"remaining_time":0.7180619722},
{"learn":[38.66881943],"iteration":531,"passed_time":0.8141013211,"remaining_time":0.7161643201},
{"learn":[38.5638241],"iteration":532,"passed_time":0.8152669779,"remaining_time":0.7143145942},
{"learn":[38.4804181],"iteration":533,"passed_time":0.8171843068,"remaining_time":0.7131233839},
{"learn":[38.3660188],"iteration":534,"passed_time":0.8183547491,"remaining_time":0.7112802959},
{"learn":[38.26881447],"iteration":535,"passed_time":0.8195009739,"remaining_time":0.7094187535},
{"learn":[38.22770369],"iteration":536,"passed_time":0.8210472399,"remaining_time":0.7079047897},
{"learn":[38.15846171],"iteration":537,"passed_time":0.8223386158,"remaining_time":0.7061718225},
{"learn":[38.08805727],"iteration":538,"passed_time":0.8234741419,"remaining_time":0.7043071974},
{"learn":[38.05916352],"iteration":539,"passed_time":0.8246326082,"remaining_time":0.7024648144},
{"learn":[38.01406015],"iteration":540,"passed_time":0.8272801217,"remaining_time":0.7018883103},
{"learn":[37.92436672],"iteration":541,"passed_time":0.8284339097,"remaining_time":0.7000419385},
{"learn":[37.84867866],"iteration":542,"passed_time":0.8295549386,"remaining_time":0.6981705468},
{"learn":[37.80653271],"iteration":543,"passed_time":0.8309490399,"remaining_time":0.6965308128},
{"learn":[37.68564695],"iteration":544,"passed_time":0.8321096181,"remaining_time":0.6946970206},
{"learn":[37.60653711],"iteration":545,"passed_time":0.8332250559,"remaining_time":0.6928281601},
{"learn":[37.55998972],"iteration":546,"passed_time":0.8342795506,"remaining_time":0.6909115839},
{"learn":[37.46446481],"iteration":547,"passed_time":0.8355629621,"remaining_time":0.6891869687},
{"learn":[37.44352572],"iteration":548,"passed_time":0.8366869889,"remaining_time":0.6873330273},
{"learn":[37.39863908],"iteration":549,"passed_time":0.8380225632,"remaining_time":0.6856548245},
{"learn":[37.31845864],"iteration":550,"passed_time":0.8392060692,"remaining_time":0.6838539475},
{"learn":[37.25170721],"iteration":551,"passed_time":0.840304611,"remaining_time":0.681986351},
{"learn":[37.15055465],"iteration":552,"passed_time":0.8414193238,"remaining_time":0.6801346071},
{"learn":[37.07353547],"iteration":553,"passed_time":0.8425936867,"remaining_time":0.6783335456},
{"learn":[37.05487684],"iteration":554,"passed_time":0.8437390676,"remaining_time":0.6765115047},
{"learn":[37.00369094],"iteration":555,"passed_time":0.8453087354,"remaining_time":0.6750307168},
{"learn":[36.93792416],"iteration":556,"passed_time":0.8471941028,"remaining_time":0.6738006957},
{"learn":[36.91929978],"iteration":557,"passed_time":0.8485012226,"remaining_time":0.6721102874},
{"learn":[36.83586842],"iteration":558,"passed_time":0.8502552194,"remaining_time":0.6707737956},
{"learn":[36.72059235],"iteration":559,"passed_time":0.8517652033,"remaining_time":0.6692440883},
{"learn":[36.62577341],"iteration":560,"passed_time":0.8531790664,"remaining_time":0.6676392337},
{"learn":[36.55606117],"iteration":561,"passed_time":0.8551467143,"remaining_time":0.6664666564},
{"learn":[36.46133019],"iteration":562,"passed_time":0.8565819795,"remaining_time":0.6648780196},
{"learn":[36.37610081],"iteration":563,"passed_time":0.8582523476,"remaining_time":0.663471673},
{"learn":[36.28454989],"iteration":564,"passed_time":0.8598261405,"remaining_time":0.6619900373},
{"learn":[36.22435595],"iteration":565,"passed_time":0.8618288731,"remaining_time":0.6608369804},
{"learn":[36.16209434],"iteration":566,"passed_time":0.8633424816,"remaining_time":0.6593073977},
{"learn":[36.12553347],"iteration":567,"passed_time":0.8646497832,"remaining_time":0.6576209619},
{"learn":[36.06346992],"iteration":568,"passed_time":0.8668891306,"remaining_time":0.6566418546},
{"learn":[35.99934613],"iteration":569,"passed_time":0.8685088798,"remaining_time":0.6551909094},
{"learn":[35.93088876],"iteration":570,"passed_time":0.8699692343,"remaining_time":0.6536196174},
{"learn":[35.85177742],"iteration":571,"passed_time":0.8714544612,"remaining_time":0.6520673241},
{"learn":[35.73837276],"iteration":572,"passed_time":0.8729580448,"remaining_time":0.6505289444},
{"learn":[35.65635286],"iteration":573,"passed_time":0.8744438884,"remaining_time":0.6489775199},
{"learn":[35.55769409],"iteration":574,"passed_time":0.875778294,"remaining_time":0.6473143912},
{"learn":[35.46872709],"iteration":575,"passed_time":0.877483324,"remaining_time":0.6459252246},
{"learn":[35.37724875],"iteration":576,"passed_time":0.8787247402,"remaining_time":0.6441950868},
{"learn":[35.31398414],"iteration":577,"passed_time":0.8799364739,"remaining_time":0.6424449688},
{"learn":[35.21716991],"iteration":578,"passed_time":0.8813765771,"remaining_time":0.6408627616},
{"learn":[35.15385985],"iteration":579,"passed_time":0.8827734883,"remaining_time":0.6392497674},
{"learn":[35.14301462],"iteration":580,"passed_time":0.8839680942,"remaining_time":0.6374916204},
{"learn":[35.06187987],"iteration":581,"passed_time":0.8852006125,"remaining_time":0.6357626392},
{"learn":[35.01708475],"iteration":582,"passed_time":0.8865032183,"remaining_time":0.6340854923},
{"learn":[34.93766246],"iteration":583,"passed_time":0.8881791399,"remaining_time":0.6326755517},
{"learn":[34.92933957],"iteration":584,"passed_time":0.8898961687,"remaining_time":0.6312938632},
{"learn":[34.86898118],"iteration":585,"passed_time":0.8912658828,"remaining_time":0.6296656578},
{"learn":[34.77606727],"iteration":586,"passed_time":0.8929271233,"remaining_time":0.6282434445},
{"learn":[34.73034008],"iteration":587,"passed_time":0.8952515375,"remaining_time":0.6272850909},
{"learn":[34.62745226],"iteration":588,"passed_time":0.8965539157,"remaining_time":0.6256089293},
{"learn":[34.61450645],"iteration":589,"passed_time":0.8982765721,"remaining_time":0.6242260925},
{"learn":[34.53034454],"iteration":590,"passed_time":0.8998228556,"remaining_time":0.6227200473},
{"learn":[34.48255707],"iteration":591,"passed_time":0.9018990927,"remaining_time":0.6215791045},
{"learn":[34.44760557],"iteration":592,"passed_time":0.9034042466,"remaining_time":0.6200430495},
{"learn":[34.36091418],"iteration":593,"passed_time":0.9046568398,"remaining_time":0.618334473},
{"learn":[34.34670557],"iteration":594,"passed_time":0.9058059771,"remaining_time":0.6165570096},
{"learn":[34.33905685],"iteration":595,"passed_time":0.9076613838,"remaining_time":0.6152604011},
{"learn":[34.26114477],"iteration":596,"passed_time":0.9089975682,"remaining_time":0.6136114238},
{"learn":[34.19782185],"iteration":597,"passed_time":0.91024804,"remaining_time":0.611905873},
{"learn":[34.12369319],"iteration":598,"passed_time":0.9118867771,"remaining_time":0.6104617656},
{"learn":[34.11150083],"iteration":599,"passed_time":0.9131467589,"remaining_time":0.6087645059},
{"learn":[34.07209301],"iteration":600,"passed_time":0.9144132527,"remaining_time":0.6070730247},
{"learn":[34.01224184],"iteration":601,"passed_time":0.9155760825,"remaining_time":0.60531442},
{"learn":[33.96554876],"iteration":602,"passed_time":0.9167197568,"remaining_time":0.6035451799},
{"learn":[33.89194277],"iteration":603,"passed_time":0.9179542215,"remaining_time":0.601837536},
{"learn":[33.80383823],"iteration":604,"passed_time":0.9191085003,"remaining_time":0.6000791035},
{"learn":[33.72317323],"iteration":605,"passed_time":0.9202233786,"remaining_time":0.5982970481},
{"learn":[33.71329882],"iteration":606,"passed_time":0.9213476017,"remaining_time":0.5965232413},
{"learn":[33.69126839],"iteration":607,"passed_time":0.9226947092,"remaining_time":0.5948952731},
{"learn":[33.60163437],"iteration":608,"passed_time":0.9238544194,"remaining_time":0.5931479113},
{"learn":[33.53100222],"iteration":609,"passed_time":0.9253639558,"remaining_time":0.5916261357},
{"learn":[33.46060826],"iteration":610,"passed_time":0.9265430467,"remaining_time":0.5898940183},
{"learn":[33.36901824],"iteration":611,"passed_time":0.927663104,"remaining_time":0.5881262816},
{"learn":[33.30454916],"iteration":612,"passed_time":0.9287834486,"remaining_time":0.5863608395},
{"learn":[33.22013054],"iteration":613,"passed_time":0.9299159759,"remaining_time":0.5846051575},
{"learn":[33.1505777],"iteration":614,"passed_time":0.9309920677,"remaining_time":0.5828161725},
{"learn":[33.08537426],"iteration":615,"passed_time":0.9320925084,"remaining_time":0.5810446805},
{"learn":[33.00691768],"iteration":616,"passed_time":0.9332182647,"remaining_time":0.5792910784},
{"learn":[32.93583662],"iteration":617,"passed_time":0.9342648871,"remaining_time":0.5774905937},
{"learn":[32.87399201],"iteration":618,"passed_time":0.9353163692,"remaining_time":0.5756955358},
{"learn":[32.83180209],"iteration":619,"passed_time":0.9364676555,"remaining_time":0.5739640469},
{"learn":[32.77823506],"iteration":620,"passed_time":0.9378401204,"remaining_time":0.5723694132},
{"learn":[32.76585703],"iteration":621,"passed_time":0.9388997449,"remaining_time":0.5705853755},
{"learn":[32.73830874],"iteration":622,"passed_time":0.9400564254,"remaining_time":0.5688623955},
{"learn":[32.72475965],"iteration":623,"passed_time":0.9411525617,"remaining_time":0.5671047487},
{"learn":[32.649049],"iteration":624,"passed_time":0.9424584123,"remaining_time":0.5654750474},
{"learn":[32.55484546],"iteration":625,"passed_time":0.9437590681,"remaining_time":0.5638432771},
{"learn":[32.50158584],"iteration":626,"passed_time":0.9455246251,"remaining_time":0.562489131},
{"learn":[32.42073928],"iteration":627,"passed_time":0.9473277351,"remaining_time":0.5611559195},
{"learn":[32.33294819],"iteration":628,"passed_time":0.9485314077,"remaining_time":0.5594676507},
{"learn":[32.28073627],"iteration":629,"passed_time":0.9497623766,"remaining_time":0.5577969513},
{"learn":[32.26901388],"iteration":630,"passed_time":0.9508736849,"remaining_time":0.5560576699},
{"learn":[32.20466898],"iteration":631,"passed_time":0.9526123501,"remaining_time":0.5546856722},
{"learn":[32.15778817],"iteration":632,"passed_time":0.953754392,"remaining_time":0.5529666064},
{"learn":[32.07650375],"iteration":633,"passed_time":0.954885949,"remaining_time":0.5512433081},
{"learn":[32.01161797],"iteration":634,"passed_time":0.9559669856,"remaining_time":0.5494928342},
{"learn":[31.97402674],"iteration":635,"passed_time":0.957109281,"remaining_time":0.5477795256},
{"learn":[31.9048986],"iteration":636,"passed_time":0.9582158126,"remaining_time":0.5460476295},
{"learn":[31.84012504],"iteration":637,"passed_time":0.9593453532,"remaining_time":0.544330749},
{"learn":[31.82218633],"iteration":638,"passed_time":0.9608465722,"remaining_time":0.5428256848},
{"learn":[31.79490335],"iteration":639,"passed_time":0.9623977783,"remaining_time":0.5413487503},
{"learn":[31.78425168],"iteration":640,"passed_time":0.9636864569,"remaining_time":0.5397245523},
{"learn":[31.72045566],"iteration":641,"passed_time":0.9649304583,"remaining_time":0.5380764861},
{"learn":[31.66579289],"iteration":642,"passed_time":0.9660681409,"remaining_time":0.5363706474},
{"learn":[31.61930573],"iteration":643,"passed_time":0.9672772669,"remaining_time":0.5347060668},
{"learn":[31.55367942],"iteration":644,"passed_time":0.9689121505,"remaining_time":0.5332772301},
{"learn":[31.54757601],"iteration":645,"passed_time":0.9701959294,"remaining_time":0.5316553545},
{"learn":[31.53829608],"iteration":646,"passed_time":0.9713569634,"remaining_time":0.529967555},
{"learn":[31.47981591],"iteration":647,"passed_time":0.9724341073,"remaining_time":0.5282358114},
{"learn":[31.46118954],"iteration":648,"passed_time":0.9734611685,"remaining_time":0.5264789987},
{"learn":[31.4133454],"iteration":649,"passed_time":0.9747321509,"remaining_time":0.5248557735},
{"learn":[31.37040795],"iteration":650,"passed_time":0.975829629,"remaining_time":0.5231406152},
{"learn":[31.32499172],"iteration":651,"passed_time":0.9769949268,"remaining_time":0.5214635499},
{"learn":[31.27190537],"iteration":652,"passed_time":0.9783367406,"remaining_time":0.5198818514},
{"learn":[31.21582065],"iteration":653,"passed_time":0.9793813987,"remaining_time":0.5181436758},
{"learn":[31.11759303],"iteration":654,"passed_time":0.9804892904,"remaining_time":0.516440924},
{"learn":[31.0392052],"iteration":655,"passed_time":0.9823004144,"remaining_time":0.5151087539},
{"learn":[31.0300281],"iteration":656,"passed_time":0.9849998901,"remaining_time":0.5142389076},
{"learn":[30.95372121],"iteration":657,"passed_time":0.9864132057,"remaining_time":0.5126950097},
{"learn":[30.88815883],"iteration":658,"passed_time":0.9880223967,"remaining_time":0.5112528639},
{"learn":[30.85189779],"iteration":659,"passed_time":0.9899273891,"remaining_time":0.5099625944},
{"learn":[30.83424599],"iteration":660,"passed_time":0.9912431358,"remaining_time":0.5083682648},
{"learn":[30.82713218],"iteration":661,"passed_time":0.9924430291,"remaining_time":0.5067156251},
{"learn":[30.77550989],"iteration":662,"passed_time":0.9935905999,"remaining_time":0.5050377559},
{"learn":[30.75880493],"iteration":663,"passed_time":0.9946992938,"remaining_time":0.5033418113},
{"learn":[30.71825075],"iteration":664,"passed_time":0.9962619822,"remaining_time":0.5018763369},
{"learn":[30.65687048],"iteration":665,"passed_time":0.9977382312,"remaining_time":0.500367221},
{"learn":[30.61448643],"iteration":666,"passed_time":0.9995728062,"remaining_time":0.4990370981},
{"learn":[30.60994171],"iteration":667,"passed_time":1.000753191,"remaining_time":0.4973803286},
{"learn":[30.54132189],"iteration":668,"passed_time":1.002002419,"remaining_time":0.4957590443},
{"learn":[30.50379851],"iteration":669,"passed_time":1.003116265,"remaining_time":0.4940721905},
{"learn":[30.40180723],"iteration":670,"passed_time":1.004253036,"remaining_time":0.4923982843},
{"learn":[30.32111974],"iteration":671,"passed_time":1.005635654,"remaining_time":0.4908459738},
{"learn":[30.24425192],"iteration":672,"passed_time":1.006981732,"remaining_time":0.4892764134},
{"learn":[30.23683721],"iteration":673,"passed_time":1.007989946,"remaining_time":0.4875440986},
{"learn":[30.17145197],"iteration":674,"passed_time":1.009057433,"remaining_time":0.4858424679},
{"learn":[30.10453511],"iteration":675,"passed_time":1.010257486,"remaining_time":0.4842062505},
{"learn":[30.041259],"iteration":676,"passed_time":1.011342455,"remaining_time":0.4825164152},
{"learn":[29.99034628],"iteration":677,"passed_time":1.012379174,"remaining_time":0.4808054483},
{"learn":[29.981459],"iteration":678,"passed_time":1.01398804,"remaining_time":0.4793669526},
{"learn":[29.92028561],"iteration":679,"passed_time":1.015349063,"remaining_time":0.4778113236},
{"learn":[29.9108751],"iteration":680,"passed_time":1.016696465,"remaining_time":0.4762498859},
{"learn":[29.90304049],"iteration":681,"passed_time":1.017856282,"remaining_time":0.4746016094},
{"learn":[29.82237932],"iteration":682,"passed_time":1.019394515,"remaining_time":0.4731303971},
{"learn":[29.81649164],"iteration":683,"passed_time":1.0206965,"remaining_time":0.471549845},
{"learn":[29.75243035],"iteration":684,"passed_time":1.02174943,"remaining_time":0.4698555772},
{"learn":[29.68657669],"iteration":685,"passed_time":1.022852193,"remaining_time":0.4681859893},
{"learn":[29.61893055],"iteration":686,"passed_time":1.024079059,"remaining_time":0.466574593},
{"learn":[29.54842593],"iteration":687,"passed_time":1.025210126,"remaining_time":0.4649208709},
{"learn":[29.49639518],"iteration":688,"passed_time":1.026244115,"remaining_time":0.4632248474},
{"learn":[29.46460351],"iteration":689,"passed_time":1.027340989,"remaining_time":0.4615589952},
{"learn":[29.41520792],"iteration":690,"passed_time":1.029193848,"remaining_time":0.4602328495},
{"learn":[29.40850482],"iteration":691,"passed_time":1.03055032,"remaining_time":0.4586842467},
{"learn":[29.3639888],"iteration":692,"passed_time":1.032631167,"remaining_time":0.4574570973},
{"learn":[29.28411942],"iteration":693,"passed_time":1.035749154,"remaining_time":0.4566847855},
{"learn":[29.26001622],"iteration":694,"passed_time":1.03728727,"remaining_time":0.4552123989},
{"learn":[29.20252878],"iteration":695,"passed_time":1.03916456,"remaining_time":0.4538879686},
{"learn":[29.19635422],"iteration":696,"passed_time":1.041198294,"remaining_time":0.4526299614},
{"learn":[29.11541314],"iteration":697,"passed_time":1.043094455,"remaining_time":0.4513102084},
{"learn":[29.10945293],"iteration":698,"passed_time":1.044752128,"remaining_time":0.4498861093},
{"learn":[29.03168875],"iteration":699,"passed_time":1.046002973,"remaining_time":0.4482869884},
{"learn":[28.9622509],"iteration":700,"passed_time":1.047323128,"remaining_time":0.4467184242},
{"learn":[28.89688725],"iteration":701,"passed_time":1.048715243,"remaining_time":0.4451811146},
{"learn":[28.83626924],"iteration":702,"passed_time":1.052772377,"remaining_time":0.4447701223},
{"learn":[28.78690837],"iteration":703,"passed_time":1.055446137,"remaining_time":0.4437671257},
{"learn":[28.71974387],"iteration":704,"passed_time":1.058209753,"remaining_time":0.4427969889},
{"learn":[28.65843745],"iteration":705,"passed_time":1.060536391,"remaining_time":0.4416398002},
{"learn":[28.60855194],"iteration":706,"passed_time":1.063230791,"remaining_time":0.440631714},
{"learn":[28.54954796],"iteration":707,"passed_time":1.065472745,"remaining_time":0.4394322622},
{"learn":[28.52585029],"iteration":708,"passed_time":1.066689987,"remaining_time":0.4378092895},
{"learn":[28.46601333],"iteration":709,"passed_time":1.068763175,"remaining_time":0.4365370716},
{"learn":[28.40672475],"iteration":710,"passed_time":1.07181484,"remaining_time":0.4356603217},
{"learn":[28.32418862],"iteration":711,"passed_time":1.07442065,"remaining_time":0.4345971168},
{"learn":[28.29299149],"iteration":712,"passed_time":1.077194486,"remaining_time":0.4335972194},
{"learn":[28.23854681],"iteration":713,"passed_time":1.078949163,"remaining_time":0.4321841184},
{"learn":[28.20431203],"iteration":714,"passed_time":1.080737964,"remaining_time":0.4307836641},
{"learn":[28.19387422],"iteration":715,"passed_time":1.081989078,"remaining_time":0.4291688522},
{"learn":[28.12610671],"iteration":716,"passed_time":1.083270294,"remaining_time":0.4275669361},
{"learn":[28.07084412],"iteration":717,"passed_time":1.084753756,"remaining_time":0.426045347},
{"learn":[28.00819571],"iteration":718,"passed_time":1.086077013,"remaining_time":0.4244612526},
{"learn":[27.97044734],"iteration":719,"passed_time":1.087499609,"remaining_time":0.4229165145},
{"learn":[27.91965703],"iteration":720,"passed_time":1.08870406,"remaining_time":0.4212877014},
{"learn":[27.87413244],"iteration":721,"passed_time":1.090056717,"remaining_time":0.4197171291},
{"learn":[27.81861499],"iteration":722,"passed_time":1.091246365,"remaining_time":0.4180847069},
{"learn":[27.7590726],"iteration":723,"passed_time":1.092403688,"remaining_time":0.4164411849},
{"learn":[27.70497082],"iteration":724,"passed_time":1.093506599,"remaining_time":0.414778365},
{"learn":[27.6308492],"iteration":725,"passed_time":1.094897446,"remaining_time":0.4132257577},
{"learn":[27.59508065],"iteration":726,"passed_time":1.096105764,"remaining_time":0.4116050531},
{"learn":[27.52843608],"iteration":727,"passed_time":1.097252326,"remaining_time":0.4099624076},
{"learn":[27.49305057],"iteration":728,"passed_time":1.09834357,"remaining_time":0.4083005589},
{"learn":[27.4429848],"iteration":729,"passed_time":1.099451883,"remaining_time":0.4066465869},
{"learn":[27.38705681],"iteration":730,"passed_time":1.100578337,"remaining_time":0.4050007832},
{"learn":[27.35161019],"iteration":731,"passed_time":1.101664943,"remaining_time":0.4033418096},
{"learn":[27.31953826],"iteration":732,"passed_time":1.102784697,"remaining_time":0.4016964722},
{"learn":[27.23006306],"iteration":733,"passed_time":1.103918653,"remaining_time":0.4000577136},
{"learn":[27.16946848],"iteration":734,"passed_time":1.104988939,"remaining_time":0.3983973724},
{"learn":[27.08200986],"iteration":735,"passed_time":1.10607505,"remaining_time":0.3967443114},
{"learn":[27.01913455],"iteration":736,"passed_time":1.107226872,"remaining_time":0.3951162378},
{"learn":[26.95862014],"iteration":737,"passed_time":1.108354664,"remaining_time":0.3934809241},
{"learn":[26.94220947],"iteration":738,"passed_time":1.109468109,"remaining_time":0.3918419166},
{"learn":[26.9144162],"iteration":739,"passed_time":1.110949953,"remaining_time":0.3903337671},
{"learn":[26.88954428],"iteration":740,"passed_time":1.112050674,"remaining_time":0.3886924757},
{"learn":[26.85099208],"iteration":741,"passed_time":1.113093996,"remaining_time":0.3870326832},
{"learn":[26.84584657],"iteration":742,"passed_time":1.114083377,"remaining_time":0.3853558922},
{"learn":[26.80044872],"iteration":743,"passed_time":1.115188481,"remaining_time":0.3837207676},
{"learn":[26.75610922],"iteration":744,"passed_time":1.116399334,"remaining_time":0.3821232618},
{"learn":[26.75068981],"iteration":745,"passed_time":1.117467203,"remaining_time":0.3804781095},
{"learn":[26.71881289],"iteration":746,"passed_time":1.118607217,"remaining_time":0.3788589369},
{"learn":[26.68176156],"iteration":747,"passed_time":1.119700632,"remaining_time":0.3772253465},
{"learn":[26.63076184],"iteration":748,"passed_time":1.120783085,"remaining_time":0.3755895252},
{"learn":[26.61520652],"iteration":749,"passed_time":1.12197051,"remaining_time":0.37399017},
{"learn":[26.56644513],"iteration":750,"passed_time":1.123159505,"remaining_time":0.3723924323},
{"learn":[26.52144924],"iteration":751,"passed_time":1.125057049,"remaining_time":0.3710294524},
{"learn":[26.473328],"iteration":752,"passed_time":1.126275191,"remaining_time":0.3694421942},
{"learn":[26.46862472],"iteration":753,"passed_time":1.127488923,"remaining_time":0.3678544763},
{"learn":[26.43498658],"iteration":754,"passed_time":1.128681632,"remaining_time":0.3662609268},
{"learn":[26.40596163],"iteration":755,"passed_time":1.129893729,"remaining_time":0.3646746956},
{"learn":[26.37125896],"iteration":756,"passed_time":1.131014247,"remaining_time":0.3630600555},
{"learn":[26.2982727],"iteration":757,"passed_time":1.132176574,"remaining_time":0.3614600672},
{"learn":[26.23991118],"iteration":758,"passed_time":1.133288658,"remaining_time":0.3598452788},
{"learn":[26.16739445],"iteration":759,"passed_time":1.134708134,"remaining_time":0.3583288845},
{"learn":[26.11458436],"iteration":760,"passed_time":1.13597485,"remaining_time":0.3567647691},
{"learn":[26.11168876],"iteration":761,"passed_time":1.136999047,"remaining_time":0.3551256866},
{"learn":[26.07627119],"iteration":762,"passed_time":1.138304741,"remaining_time":0.3535756536},
{"learn":[26.04114547],"iteration":763,"passed_time":1.139506182,"remaining_time":0.3519940564},
{"learn":[26.00800285],"iteration":764,"passed_time":1.141636704,"remaining_time":0.3506988566},
{"learn":[25.99804221],"iteration":765,"passed_time":1.143203263,"remaining_time":0.3492291953},
{"learn":[25.94758767],"iteration":766,"passed_time":1.145127063,"remaining_time":0.3478678039},
{"learn":[25.88803284],"iteration":767,"passed_time":1.146522073,"remaining_time":0.3463452097},
{"learn":[25.80962316],"iteration":768,"passed_time":1.147810292,"remaining_time":0.3447908678},
{"learn":[25.74515449],"iteration":769,"passed_time":1.149349442,"remaining_time":0.3433121709},
{"learn":[25.72338155],"iteration":770,"passed_time":1.150466711,"remaining_time":0.3417080114},
{"learn":[25.69729137],"iteration":771,"passed_time":1.151532726,"remaining_time":0.3400899762},
{"learn":[25.6265003],"iteration":772,"passed_time":1.153125503,"remaining_time":0.3386280583},
{"learn":[25.56683533],"iteration":773,"passed_time":1.154184508,"remaining_time":0.3370099466},
{"learn":[25.53015268],"iteration":774,"passed_time":1.155658123,"remaining_time":0.3355136485},
{"learn":[25.47911327],"iteration":775,"passed_time":1.157034069,"remaining_time":0.3339892159},
{"learn":[25.42044429],"iteration":776,"passed_time":1.158164324,"remaining_time":0.3323946515},
{"learn":[25.39566222],"iteration":777,"passed_time":1.159513544,"remaining_time":0.3308637619},
{"learn":[25.3439084],"iteration":778,"passed_time":1.160825416,"remaining_time":0.3293227432},
{"learn":[25.30213086],"iteration":779,"passed_time":1.162084573,"remaining_time":0.3277674437},
{"learn":[25.24508756],"iteration":780,"passed_time":1.1634875,"remaining_time":0.3262532169},
{"learn":[25.20572919],"iteration":781,"passed_time":1.164574196,"remaining_time":0.3246511185},
{"learn":[25.17377531],"iteration":782,"passed_time":1.165691479,"remaining_time":0.3230588136},
{"learn":[25.13243708],"iteration":783,"passed_time":1.16714288,"remaining_time":0.321559773},
{"learn":[25.07247493],"iteration":784,"passed_time":1.168382413,"remaining_time":0.3200028265},
{"learn":[25.01753774],"iteration":785,"passed_time":1.169461003,"remaining_time":0.3184028685},
{"learn":[24.9880763],"iteration":786,"passed_time":1.171102365,"remaining_time":0.3169565485},
{"learn":[24.92881175],"iteration":787,"passed_time":1.172384586,"remaining_time":0.315413112},
{"learn":[24.86441029],"iteration":788,"passed_time":1.173461641,"remaining_time":0.3138154706},
{"learn":[24.83143847],"iteration":789,"passed_time":1.174782743,"remaining_time":0.3122840202},
{"learn":[24.82914581],"iteration":790,"passed_time":1.175924149,"remaining_time":0.3107056221},
{"learn":[24.80546729],"iteration":791,"passed_time":1.176944039,"remaining_time":0.3090964142},
{"learn":[24.77204052],"iteration":792,"passed_time":1.178194418,"remaining_time":0.3075488582},
{"learn":[24.76854096],"iteration":793,"passed_time":1.17936381,"remaining_time":0.305981039},
{"learn":[24.70043523],"iteration":794,"passed_time":1.18065466,"remaining_time":0.3044455412},
{"learn":[24.68485914],"iteration":795,"passed_time":1.182167382,"remaining_time":0.30296752},
{"learn":[24.65353993],"iteration":796,"passed_time":1.18338481,"remaining_time":0.3014141987},
{"learn":[24.58828546],"iteration":797,"passed_time":1.184516559,"remaining_time":0.2998400312},
{"learn":[24.54961908],"iteration":798,"passed_time":1.186103213,"remaining_time":0.2983814091},
{"learn":[24.5418362],"iteration":799,"passed_time":1.187710153,"remaining_time":0.2969275381},
{"learn":[24.49823973],"iteration":800,"passed_time":1.188899561,"remaining_time":0.295369554},
{"learn":[24.44703894],"iteration":801,"passed_time":1.189904028,"remaining_time":0.2937668298},
{"learn":[24.41684307],"iteration":802,"passed_time":1.191387128,"remaining_time":0.2922830189},
{"learn":[24.35833719],"iteration":803,"passed_time":1.192433325,"remaining_time":0.2906927011},
{"learn":[24.30592789],"iteration":804,"passed_time":1.19363834,"remaining_time":0.2891422067},
{"learn":[24.26121829],"iteration":805,"passed_time":1.19509599,"remaining_time":0.2876533773},
{"learn":[24.19932025],"iteration":806,"passed_time":1.196371969,"remaining_time":0.2861211772},
{"learn":[24.16502969],"iteration":807,"passed_time":1.19782114,"remaining_time":0.284630766},
{"learn":[24.11989893],"iteration":808,"passed_time":1.198933675,"remaining_time":0.2830609788},
{"learn":[24.06742191],"iteration":809,"passed_time":1.200305717,"remaining_time":0.2815531929},
{"learn":[24.03505877],"iteration":810,"passed_time":1.202301713,"remaining_time":0.2801911513},
{"learn":[23.97411085],"iteration":811,"passed_time":1.203831449,"remaining_time":0.2787195966},
{"learn":[23.93884973],"iteration":812,"passed_time":1.206102626,"remaining_time":0.2774184392},
{"learn":[23.89500662],"iteration":813,"passed_time":1.208095835,"remaining_time":0.2760513825},
{"learn":[23.84236501],"iteration":814,"passed_time":1.209887506,"remaining_time":0.2746370412},
{"learn":[23.8086382],"iteration":815,"passed_time":1.211088088,"remaining_time":0.2730884903},
{"learn":[23.77492855],"iteration":816,"passed_time":1.212602088,"remaining_time":0.2716109939},
{"learn":[23.72465862],"iteration":817,"passed_time":1.213720598,"remaining_time":0.2700454143},
{"learn":[23.71755719],"iteration":818,"passed_time":1.215319732,"remaining_time":0.2685871447},
{"learn":[23.67991383],"iteration":819,"passed_time":1.217273941,"remaining_time":0.2672064749},
{"learn":[23.67719295],"iteration":820,"passed_time":1.218774603,"remaining_time":0.2657255224},
{"learn":[23.63956564],"iteration":821,"passed_time":1.22009413,"remaining_time":0.2642052982},
{"learn":[23.61888438],"iteration":822,"passed_time":1.221367791,"remaining_time":0.2626756975},
{"learn":[23.57423861],"iteration":823,"passed_time":1.222601345,"remaining_time":0.2611381514},
{"learn":[23.53444355],"iteration":824,"passed_time":1.223941835,"remaining_time":0.2596240256},
{"learn":[23.49913569],"iteration":825,"passed_time":1.225132031,"remaining_time":0.2580786602},
{"learn":[23.49515155],"iteration":826,"passed_time":1.226331678,"remaining_time":0.256536131},
{"learn":[23.44398296],"iteration":827,"passed_time":1.227801655,"remaining_time":0.2550505853},
{"learn":[23.40611292],"iteration":828,"passed_time":1.228989551,"remaining_time":0.2535068917},
{"learn":[23.36739769],"iteration":829,"passed_time":1.230221051,"remaining_time":0.2519729864},
{"learn":[23.3402969],"iteration":830,"passed_time":1.232020727,"remaining_time":0.2505553584},
{"learn":[23.28590283],"iteration":831,"passed_time":1.233286919,"remaining_time":0.2490290895},
{"learn":[23.23220769],"iteration":832,"passed_time":1.234714276,"remaining_time":0.2475357551},
{"learn":[23.21207581],"iteration":833,"passed_time":1.235815089,"remaining_time":0.2459775836},
{"learn":[23.15557776],"iteration":834,"passed_time":1.236967597,"remaining_time":0.2444307227},
{"learn":[23.10337067],"iteration":835,"passed_time":1.238762191,"remaining_time":0.2430107648},
{"learn":[23.06158621],"iteration":836,"passed_time":1.240196039,"remaining_time":0.2415196587},
{"learn":[23.04528916],"iteration":837,"passed_time":1.241426414,"remaining_time":0.2399893546},
{"learn":[23.01934821],"iteration":838,"passed_time":1.242870929,"remaining_time":0.2385008577},
{"learn":[22.98446334],"iteration":839,"passed_time":1.244144003,"remaining_time":0.2369798101},
{"learn":[22.96837803],"iteration":840,"passed_time":1.245960763,"remaining_time":0.2355621419},
{"learn":[22.92884037],"iteration":841,"passed_time":1.247944754,"remaining_time":0.2341749063},
{"learn":[22.88859187],"iteration":842,"passed_time":1.249541016,"remaining_time":0.2327140444},
{"learn":[22.84772852],"iteration":843,"passed_time":1.250787477,"remaining_time":0.2311882066},
{"learn":[22.79710782],"iteration":844,"passed_time":1.252373519,"remaining_time":0.22972532},
{"learn":[22.75575849],"iteration":845,"passed_time":1.253961866,"remaining_time":0.2282625619},
{"learn":[22.73364276],"iteration":846,"passed_time":1.25550354,"remaining_time":0.2267910764},
{"learn":[22.69261645],"iteration":847,"passed_time":1.25713487,"remaining_time":0.2253354956},
{"learn":[22.64833118],"iteration":848,"passed_time":1.25882672,"remaining_time":0.2238902647},
{"learn":[22.59447196],"iteration":849,"passed_time":1.259966539,"remaining_time":0.2223470363},
{"learn":[22.57536958],"iteration":850,"passed_time":1.26113543,"remaining_time":0.2208098461},
{"learn":[22.5190155],"iteration":851,"passed_time":1.263125599,"remaining_time":0.2194161838},
{"learn":[22.47332838],"iteration":852,"passed_time":1.264356949,"remaining_time":0.2178903534},
{"learn":[22.44210525],"iteration":853,"passed_time":1.265884675,"remaining_time":0.2164158812},
{"learn":[22.40779067],"iteration":854,"passed_time":1.267081775,"remaining_time":0.2148852133},
{"learn":[22.35773019],"iteration":855,"passed_time":1.26824172,"remaining_time":0.2133490744},
{"learn":[22.32449568],"iteration":856,"passed_time":1.26993971,"remaining_time":0.2119035922},
{"learn":[22.29211653],"iteration":857,"passed_time":1.270991351,"remaining_time":0.2103505499},
{"learn":[22.23285574],"iteration":858,"passed_time":1.272039489,"remaining_time":0.2087981},
{"learn":[22.19605883],"iteration":859,"passed_time":1.27330401,"remaining_time":0.2072820481},
{"learn":[22.18607797],"iteration":860,"passed_time":1.274408717,"remaining_time":0.2057407801},
{"learn":[22.15168551],"iteration":861,"passed_time":1.275433951,"remaining_time":0.204187802},
{"learn":[22.10804262],"iteration":862,"passed_time":1.276754414,"remaining_time":0.202682914},
{"learn":[22.08655759],"iteration":863,"passed_time":1.278377246,"remaining_time":0.2012260479},
{"learn":[22.04990705],"iteration":864,"passed_time":1.279409176,"remaining_time":0.1996765766},
{"learn":[22.02826724],"iteration":865,"passed_time":1.28062222,"remaining_time":0.198156325},
{"learn":[21.97310722],"iteration":866,"passed_time":1.281646149,"remaining_time":0.1966077714},
{"learn":[21.94436402],"iteration":867,"passed_time":1.282714074,"remaining_time":0.1950671172},
{"learn":[21.89099763],"iteration":868,"passed_time":1.283981541,"remaining_time":0.1935576315},
{"learn":[21.83445432],"iteration":869,"passed_time":1.28510372,"remaining_time":0.1920269927},
{"learn":[21.79285357],"iteration":870,"passed_time":1.286251186,"remaining_time":0.1905010368},
{"learn":[21.76694827],"iteration":871,"passed_time":1.287739761,"remaining_time":0.18902602},
{"learn":[21.7283219],"iteration":872,"passed_time":1.289032254,"remaining_time":0.1875224471},
{"learn":[21.68288034],"iteration":873,"passed_time":1.290196163,"remaining_time":0.1860008199},
{"learn":[21.64121485],"iteration":874,"passed_time":1.291567984,"remaining_time":0.184509712},
{"learn":[21.63502674],"iteration":875,"passed_time":1.293104337,"remaining_time":0.1830421664},
{"learn":[21.60381311],"iteration":876,"passed_time":1.294230144,"remaining_time":0.1815168845},
{"learn":[21.55887848],"iteration":877,"passed_time":1.295656563,"remaining_time":0.1800342833},
{"learn":[21.5307372],"iteration":878,"passed_time":1.296981647,"remaining_time":0.1785378603},
{"learn":[21.481224],"iteration":879,"passed_time":1.298377183,"remaining_time":0.1770514341},
{"learn":[21.4502728],"iteration":880,"passed_time":1.299801808,"remaining_time":0.1755691432},
{"learn":[21.41655234],"iteration":881,"passed_time":1.300916838,"remaining_time":0.1740455634},
{"learn":[21.3834841],"iteration":882,"passed_time":1.302306841,"remaining_time":0.1725593436},
{"learn":[21.36668702],"iteration":883,"passed_time":1.303510314,"remaining_time":0.1710488647},
{"learn":[21.33973025],"iteration":884,"passed_time":1.30475173,"remaining_time":0.1695440101},
{"learn":[21.3356683],"iteration":885,"passed_time":1.306030627,"remaining_time":0.1680445728},
{"learn":[21.3070073],"iteration":886,"passed_time":1.307356767,"remaining_time":0.1665516513},
{"learn":[21.25947307],"iteration":887,"passed_time":1.308852202,"remaining_time":0.1650804579},
{"learn":[21.2330222],"iteration":888,"passed_time":1.310535261,"remaining_time":0.1636326366},
{"learn":[21.17909311],"iteration":889,"passed_time":1.311667681,"remaining_time":0.1621162302},
{"learn":[21.1774476],"iteration":890,"passed_time":1.31364588,"remaining_time":0.1607041537},
{"learn":[21.14731235],"iteration":891,"passed_time":1.314838823,"remaining_time":0.1591957319},
{"learn":[21.09614466],"iteration":892,"passed_time":1.316252447,"remaining_time":0.1577144589},
{"learn":[21.08031076],"iteration":893,"passed_time":1.317760739,"remaining_time":0.1562445618},
{"learn":[21.05679245],"iteration":894,"passed_time":1.319614765,"remaining_time":0.15481514},
{"learn":[21.02485203],"iteration":895,"passed_time":1.321054197,"remaining_time":0.1533366479},
{"learn":[21.00022569],"iteration":896,"passed_time":1.322940731,"remaining_time":0.1519095822},
{"learn":[20.9692209],"iteration":897,"passed_time":1.3247996,"remaining_time":0.150478351},
{"learn":[20.95880245],"iteration":898,"passed_time":1.327646396,"remaining_time":0.1491571591},
{"learn":[20.94794025],"iteration":899,"passed_time":1.329531857,"remaining_time":0.1477257619},
{"learn":[20.89167821],"iteration":900,"passed_time":1.330831061,"remaining_time":0.1462289401},
{"learn":[20.83947336],"iteration":901,"passed_time":1.33242704,"remaining_time":0.1447648004},
{"learn":[20.80539301],"iteration":902,"passed_time":1.334250675,"remaining_time":0.1433248234},
{"learn":[20.7929203],"iteration":903,"passed_time":1.335571391,"remaining_time":0.1418305902},
{"learn":[20.74175838],"iteration":904,"passed_time":1.337160072,"remaining_time":0.1403648694},
{"learn":[20.70983609],"iteration":905,"passed_time":1.338865453,"remaining_time":0.1389109852},
{"learn":[20.6694257],"iteration":906,"passed_time":1.339868455,"remaining_time":0.1373845274},
{"learn":[20.63756204],"iteration":907,"passed_time":1.341153635,"remaining_time":0.1358878133},
{"learn":[20.59092023],"iteration":908,"passed_time":1.342274564,"remaining_time":0.1343751213},
{"learn":[20.5358838],"iteration":909,"passed_time":1.34327241,"remaining_time":0.1328511174},
{"learn":[20.49320321],"iteration":910,"passed_time":1.344369011,"remaining_time":0.1313379166},
{"learn":[20.44942947],"iteration":911,"passed_time":1.345426686,"remaining_time":0.1298218732},
{"learn":[20.40521913],"iteration":912,"passed_time":1.346458083,"remaining_time":0.1283043299},
{"learn":[20.36529972],"iteration":913,"passed_time":1.347464887,"remaining_time":0.1267855364},
{"learn":[20.32024969],"iteration":914,"passed_time":1.348620506,"remaining_time":0.1252816864},
{"learn":[20.28693419],"iteration":915,"passed_time":1.349726613,"remaining_time":0.1237740563},
{"learn":[20.27428828],"iteration":916,"passed_time":1.350843744,"remaining_time":0.1222682996},
{"learn":[20.25192145],"iteration":917,"passed_time":1.352303637,"remaining_time":0.1207940068},
{"learn":[20.22001221],"iteration":918,"passed_time":1.353382989,"remaining_time":0.1192862047},
{"learn":[20.21034202],"iteration":919,"passed_time":1.354603631,"remaining_time":0.1177916201},
{"learn":[20.1708365],"iteration":920,"passed_time":1.355928802,"remaining_time":0.1163065965},
{"learn":[20.16051354],"iteration":921,"passed_time":1.356937864,"remaining_time":0.1147951772},
{"learn":[20.13250106],"iteration":922,"passed_time":1.357995068,"remaining_time":0.1132888627},
{"learn":[20.10633254],"iteration":923,"passed_time":1.359008701,"remaining_time":0.1117799365},
{"learn":[20.07659622],"iteration":924,"passed_time":1.360036424,"remaining_time":0.1102732236},
{"learn":[20.06350371],"iteration":925,"passed_time":1.361052201,"remaining_time":0.1087665906},
{"learn":[20.04001493],"iteration":926,"passed_time":1.362082709,"remaining_time":0.1072621766},
{"learn":[19.99907545],"iteration":927,"passed_time":1.363326111,"remaining_time":0.1057753017},
{"learn":[19.97766858],"iteration":928,"passed_time":1.364331145,"remaining_time":0.1042707333},
{"learn":[19.96927428],"iteration":929,"passed_time":1.365372823,"remaining_time":0.1027699974},
{"learn":[19.94119903],"iteration":930,"passed_time":1.366696252,"remaining_time":0.1012911293},
{"learn":[19.91491089],"iteration":931,"passed_time":1.367846806,"remaining_time":0.09979998156},
{"learn":[19.87329956],"iteration":932,"passed_time":1.36932186,"remaining_time":0.09833286672},
{"learn":[19.85397457],"iteration":933,"passed_time":1.370664203,"remaining_time":0.09685635692},
{"learn":[19.85175861],"iteration":934,"passed_time":1.371702308,"remaining_time":0.09535898396},
{"learn":[19.83359464],"iteration":935,"passed_time":1.372694937,"remaining_time":0.09385948286},
{"learn":[19.81207014],"iteration":936,"passed_time":1.373882882,"remaining_time":0.0923741959},
{"learn":[19.80559686],"iteration":937,"passed_time":1.374958694,"remaining_time":0.09088213115},
{"learn":[19.79014594],"iteration":938,"passed_time":1.37595447,"remaining_time":0.08938575366},
{"learn":[19.76445945],"iteration":939,"passed_time":1.37694255,"remaining_time":0.08788995002},
{"learn":[19.74554659],"iteration":940,"passed_time":1.377900019,"remaining_time":0.08639330618},
{"learn":[19.71230811],"iteration":941,"passed_time":1.378856759,"remaining_time":0.08489776222},
{"learn":[19.6781543],"iteration":942,"passed_time":1.379895444,"remaining_time":0.08340831424},
{"learn":[19.65057366],"iteration":943,"passed_time":1.380926575,"remaining_time":0.0819193731},
{"learn":[19.62979407],"iteration":944,"passed_time":1.382096244,"remaining_time":0.08043946395},
{"learn":[19.6058578],"iteration":945,"passed_time":1.38317995,"remaining_time":0.07895530371},
{"learn":[19.57046178],"iteration":946,"passed_time":1.384393459,"remaining_time":0.0774792538},
{"learn":[19.5593971],"iteration":947,"passed_time":1.385881534,"remaining_time":0.07601881833},
{"learn":[19.54683013],"iteration":948,"passed_time":1.386986582,"remaining_time":0.07453774043},
{"learn":[19.52442382],"iteration":949,"passed_time":1.3881059,"remaining_time":0.07305820525},
{"learn":[19.50352784],"iteration":950,"passed_time":1.389094923,"remaining_time":0.07157271423},
{"learn":[19.46200804],"iteration":951,"passed_time":1.390062303,"remaining_time":0.07008717493},
{"learn":[19.42708086],"iteration":952,"passed_time":1.391089967,"remaining_time":0.06860569619},
{"learn":[19.3883326],"iteration":953,"passed_time":1.392079567,"remaining_time":0.06712333341},
{"learn":[19.36003402],"iteration":954,"passed_time":1.39304415,"remaining_time":0.06564082381},
{"learn":[19.32463323],"iteration":955,"passed_time":1.394055489,"remaining_time":0.06416154972},
{"learn":[19.29009768],"iteration":956,"passed_time":1.395090211,"remaining_time":0.06268430417},
{"learn":[19.25632864],"iteration":957,"passed_time":1.396074309,"remaining_time":0.06120576301},
{"learn":[19.24224374],"iteration":958,"passed_time":1.397104125,"remaining_time":0.05973020763},
{"learn":[19.20866773],"iteration":959,"passed_time":1.39818067,"remaining_time":0.05825752793},
{"learn":[19.17666616],"iteration":960,"passed_time":1.399442748,"remaining_time":0.05679320206},
{"learn":[19.15534006],"iteration":961,"passed_time":1.400644618,"remaining_time":0.05532691839},
{"learn":[19.13228436],"iteration":962,"passed_time":1.401635509,"remaining_time":0.0538530777},
{"learn":[19.10696805],"iteration":963,"passed_time":1.402663968,"remaining_time":0.05238164194},
{"learn":[19.06663339],"iteration":964,"passed_time":1.403670265,"remaining_time":0.05091032051},
{"learn":[19.02928359],"iteration":965,"passed_time":1.404689226,"remaining_time":0.04944040752},
{"learn":[18.99083198],"iteration":966,"passed_time":1.405666222,"remaining_time":0.04796999517},
{"learn":[18.96924525],"iteration":967,"passed_time":1.406676665,"remaining_time":0.04650170794},
{"learn":[18.91658451],"iteration":968,"passed_time":1.407679799,"remaining_time":0.04503413187},
{"learn":[18.89323182],"iteration":969,"passed_time":1.408731713,"remaining_time":0.04356902204},
{"learn":[18.86030283],"iteration":970,"passed_time":1.40974073,"remaining_time":0.04210348215},
{"learn":[18.81916311],"iteration":971,"passed_time":1.410723756,"remaining_time":0.04063813288},
{"learn":[18.80807597],"iteration":972,"passed_time":1.411740064,"remaining_time":0.03917469858},
{"learn":[18.76845026],"iteration":973,"passed_time":1.412829943,"remaining_time":0.03771414632},
{"learn":[18.7574173],"iteration":974,"passed_time":1.413818715,"remaining_time":0.03625176193},
{"learn":[18.7293902],"iteration":975,"passed_time":1.414979889,"remaining_time":0.03479458743},
{"learn":[18.69887382],"iteration":976,"passed_time":1.415988166,"remaining_time":0.03333441947},
{"learn":[18.69566339],"iteration":977,"passed_time":1.416943104,"remaining_time":0.03187397576},
{"learn":[18.66309896],"iteration":978,"passed_time":1.417924612,"remaining_time":0.03041513468},
{"learn":[18.64822443],"iteration":979,"passed_time":1.418961587,"remaining_time":0.02895839974},
{"learn":[18.63961228],"iteration":980,"passed_time":1.419934202,"remaining_time":0.02750127405},
{"learn":[18.61234435],"iteration":981,"passed_time":1.420942965,"remaining_time":0.02604579774},
{"learn":[18.58398554],"iteration":982,"passed_time":1.422390735,"remaining_time":0.02459882247},
{"learn":[18.55432109],"iteration":983,"passed_time":1.42337326,"remaining_time":0.02314428065},
{"learn":[18.53633139],"iteration":984,"passed_time":1.424365752,"remaining_time":0.02169084902},
{"learn":[18.50608786],"iteration":985,"passed_time":1.425418992,"remaining_time":0.02023921489},
{"learn":[18.48882973],"iteration":986,"passed_time":1.426511573,"remaining_time":0.01878890622},
{"learn":[18.45481699],"iteration":987,"passed_time":1.427665298,"remaining_time":0.01734006435},
{"learn":[18.43342639],"iteration":988,"passed_time":1.428854008,"remaining_time":0.01589220838},
{"learn":[18.39712393],"iteration":989,"passed_time":1.430175753,"remaining_time":0.01444621973},
{"learn":[18.37476305],"iteration":990,"passed_time":1.431419517,"remaining_time":0.01299977361},
{"learn":[18.33611867],"iteration":991,"passed_time":1.432800765,"remaining_time":0.01155484488},
{"learn":[18.28972825],"iteration":992,"passed_time":1.433974627,"remaining_time":0.01010858246},
{"learn":[18.25618686],"iteration":993,"passed_time":1.435228816,"remaining_time":0.008663353015},
{"learn":[18.23632036],"iteration":994,"passed_time":1.43641833,"remaining_time":0.007218182564},
{"learn":[18.19109923],"iteration":995,"passed_time":1.437653667,"remaining_time":0.005773709505},
{"learn":[18.1590129],"iteration":996,"passed_time":1.438936361,"remaining_time":0.004329798479},
{"learn":[18.13257651],"iteration":997,"passed_time":1.440316769,"remaining_time":0.002886406352},
{"learn":[18.10033434],"iteration":998,"passed_time":1.441469227,"remaining_time":0.001442912139},
{"learn":[18.0807523],"iteration":999,"passed_time":1.442630456,"remaining_time":0}
]}